Workbook

Sheet Planilha1
A1: VENDEDOR | B1: DATA DE ENTRADA | C1: GRUPO DE CLIENTE | D1: PEDIDO | E1: CLIENTE | F1: PRODUTO | G1: GRUPO | H1: LINHA | I1: QUANTIDADE | J1: PREÇO UNITARIO | K1: TOTAL | L1: DATA DE ENTREGA | M1: STATUS | N1: DATA DE SAIDA | O1: MATERIA PRIMA | P1: CORTE | Q1: SILK | R1: COSTURA | S1: EMBALAGEM | T1: NF | U1: ENTREGA
A2: LETICIA | B2: 45538 | C2: COSMÉTICO | D2: 598 | E2: GARDEN INDUSTRIA | F2: CAPA DE CORTE CETIM 1,47A X 1,20L SUBLIMADA COM ZIPER | G2: CAPA | H2: LEVE | I2: 300 | J2: 28 | K2: =I2*J2 -> 8400 | L2: 45567 | M2: =IF(L2<TODAY(),"ATRASO","EM PRODUÇÃO") -> ATRASO | N2: FALTA 54 PEÇAS | O2: OK | P2: OK | Q2: OK | R2: OK | S2: OK | T2: 970 | U2: ENTREGUE
A3: LETICIA | B3: 45553 | C3: COSMÉTICO | D3: 180 | E3: NB COSMÉTICOS (D BIANCO) | F3: KIMONO CETIM - TAM ÚNICO | G3: KIMONO | H3: LEVE | I3: 100 | J3: 26.5 | K3: =I3*J3 -> 2650 | L3: 45580 | M3: =IF(L3<TODAY(),"ATRASO","EM PRODUÇÃO") -> ATRASO | N3: 45589 | O3: OK | P3: OK | Q3: OK | R3: OK | S3: OK | T3: OK | U3: ENTREGUE
A4: LETICIA | B4: 45552 | C4: PET | D4: 176 | E4: PETCO CLEAN & CARE (PETCO) | F4: CAMISETA POLO MALHA PIQUET | G4: CAMISETA | H4: LEVE | I4: 10 | J4: 75 | K4: =I4*J4 -> 750 | L4: 45580 | M4: =IF(L4<TODAY(),"ATRASO","EM PRODUÇÃO") -> ATRASO | N4: 45594 | O4: OK | P4: OK | Q4: OK | R4: OK | S4: OK | T4: 154 | U4: ENTREGUE
A5: LETICIA | B5: 45552 | C5: PET | D5: 177 | E5: PETCO CLEAN & CARE (PETCO) | F5: JALECO MICROFIBRA COM TAFETA- PETCO | G5: JALECO | H5: LEVE | I5: 210 | J5: 55 | K5: =I5*J5 -> 11550 | L5: 45580 | M5: =IF(L5<TODAY(),"ATRASO","EM PRODUÇÃO") -> ATRASO | N5: 45596 | O5: OK | P5: OK | Q5: OK | R5: OK | S5: OK | T5: OK | U5: ENTREGUE
A6: LETICIA | B6: 45552 | C6: CONSUMIDOR FINAL | D6: 179 | E6: NOEME SERRA PAIXÃO | F6: SACOLA NYLON 600 42L X 32A X 20 FOLY COM DIVISORIA | G6: SACOLA | H6: AMBAS | I6: 112 | J6: 23.5 | K6: =I6*J6 -> 2632 | L6: 45580 | M6: =IF(L6<TODAY(),"ATRASO","EM PRODUÇÃO") -> ATRASO | O6: OK | P6: OK | Q6: OK | R6: OK | S6: OK | T6: OK | U6: ENTREGUE
A7: LETICIA | B7: 45553 | C7: PET | D7: 181 | E7: CHEMVET (PETSPA) | F7: JALECO MICROFIBRA COM TAFETA- PETSPA | G7: JALECO | H7: LEVE | I7: 200 | J7: 55 | K7: =I7*J7 -> 11000 | L7: 45581 | M7: =IF(L7<TODAY(),"ATRASO","EM PRODUÇÃO") -> ATRASO | N7: 45602 | O7: OK | P7: OK | Q7: OK | R7: OK | S7: OK | T7: 159 | U7: ENTREGUE
A8: LETICIA | B8: 45572 | C8: COSMÉTICO | D8: 616 | E8: FLORA DISTRIBUIDORA | F8: CAMISETA MALHA PV GOLA CARECA | G8: CAMISETA | H8: LEVE | I8: 112 | J8: 26.5 | K8: =I8*J8 -> 2968 | L8: 45586 | M8: =IF(L8<TODAY(),"ATRASO","EM PRODUÇÃO") -> ATRASO | N8: 45587 | O8: OK | P8: OK | Q8: OK | R8: OK | S8: OK | T8: 959 | U8: ENTREGUE
A9: LETICIA | B9: 45560 | C9: COSMÉTICO | D9: 187 | E9: DUO INDUSTRIA (KPRO) | F9: AVENTAL GABARDINE MODELO PADRÃO | G9: AVENTAL | H9: LEVE | I9: 500 | J9: 19.5 | K9: =I9*J9 -> 9750 | L9: 45588 | M9: =IF(L9<TODAY(),"ATRASO","EM PRODUÇÃO") -> ATRASO | N9: 45600 | O9: OK | P9: OK | Q9: OK | R9: OK | S9: OK | T9: 158 | U9: ENTREGUE
A10: LETICIA | B10: 45574 | C10: COSMÉTICO | D10: 619 | E10: M.D BOSO PROHALL | F10: CAMISETA GOLA CARECA MALHA PV | G10: CAMISETA | H10: LEVE | I10: 34 | J10: 24.5 | K10: =I10*J10 -> 833 | L10: 45590 | M10: =IF(L10<TODAY(),"ATRASO","EM PRODUÇÃO") -> ATRASO | N10: 45588 | O10: OK | P10: OK | Q10: OK | R10: ok | S10: OK | T10: 961 | U10: ENTREGUE
A11: LETICIA | B11: 45565 | C11: EDITORA | D11: 1023 | E11: EDITORA RECORD | F11: SACOLA ALGODÃO CRU 35L X 40A | G11: SACOLA | H11: LEVE | I11: 400 | J11: 10.5 | K11: =I11*J11 -> 4200 | L11: 45593 | M11: =IF(L11<TODAY(),"ATRASO","EM PRODUÇÃO") -> ATRASO | O11: OK | P11: OK | Q11: OK | R11: OK | S11: OK | T11: OK | U11: ENTREGUE
A12: LETICIA | B12: 45561 | C12: COSMÉTICO | D12: 608 | E12: BR COSMETIC | F12: NECESSAIRE MALETA CRISTAL COLORIDO | G12: NECESSAIRE | H12: PESADA | I12: 1000 | J12: 15.5 | K12: =I12*J12 -> 15500 | L12: 45593 | M12: =IF(L12<TODAY(),"ATRASO","EM PRODUÇÃO") -> ATRASO | N12: 45588 | O12: OK | P12: OK | Q12: OK | R12: OK | S12: OK | T12: OK | U12: ENTREGUE
A13: DANIELE | B13: 45566 | C13: COSMÉTICO | D13: 190 | E13: FILO COSMETICOS | F13: NECESSAIRE CRISTAL COM VIES | G13: NECESSAIRE | H13: PESADA | I13: 100 | J13: 12 | K13: =I13*J13 -> 1200 | L13: 45594 | M13: =IF(L13<TODAY(),"ATRASO","EM PRODUÇÃO") -> ATRASO | N13: 41212 | O13: OK | P13: OK | Q13: OK | R13: OK | S13: OK | T13: OK | U13: ENTREGUE
A14: LETICIA | B14: 45565 | C14: PET | D14: 189 | E14: VET RIO | F14: AVENTAL SEMI IMPERMEAVEL | G14: AVENTAL | H14: LEVE | I14: 100 | J14: 19.7 | K14: =I14*J14 -> 1970 | L14: 45593 | M14: =IF(L14<TODAY(),"ATRASO","EM PRODUÇÃO") -> ATRASO | N14: 45596 | O14: OK | P14: OK | Q14: OK | R14: OK | S14: OK | T14: 157 | U14: ENTREGUE
A15: DANIELE | B15: 45566 | C15: COSMÉTICO | D15: 190 | E15: FILO COSMETICOS | F15: AVENTAL OXFORD MODELO PADRÃO | G15: AVENTAL | H15: LEVE | I15: 100 | J15: 17 | K15: =I15*J15 -> 1700 | L15: 45594 | M15: =IF(L15<TODAY(),"ATRASO","EM PRODUÇÃO") -> ATRASO | N15: 45595 | O15: OK | P15: OK | Q15: OK | R15: OK | S15: OK | T15: OK | U15: ENTREGUE
A16: LETICIA | B16: 45555 | C16: HAVANNA | D16: 1015 | E16: DOCES E DOCES (HAVANNA PRAIA DE BELLAS) | F16: CAMISETA GOLA CARECA MALHA 100% ALGODÃO | G16: CAMISETA | H16: LEVE | I16: =10+10+10+10+5 -> 45 | J16: 36.75 | K16: =I16*J16 -> 1653.75 | L16: 45593 | M16: =IF(L16<TODAY(),"ATRASO","EM PRODUÇÃO") -> ATRASO | O16: OK | P16: OK | Q16: OK | R16: OK | S16: OK | T16: OK | U16: ENTREGUE
A17: LETICIA | B17: 45567 | C17: COSMÉTICO | D17: 614 | E17: KOOSMETICS (EXO) | F17: NECESSSAIRE CRISTAL 30A X 16L X 10 - EXO | G17: NECESSAIRE | H17: PESADA | I17: 1500 | J17: 7.8 | K17: =I17*J17 -> 11700 | L17: 45595 | M17: =IF(L17<TODAY(),"ATRASO","EM PRODUÇÃO") -> ATRASO | N17: 45590 | O17: OK | P17: OK | Q17: OK | R17: OK | S17: OK | T17: 953 | U17: ENTREGUE
A18: LETICIA | B18: 45555 | C18: HAVANNA | D18: 1015 | E18: DOCES E DOCES (HAVANNA PRAIA DE BELLAS) | F18: CAMISETA FEMININA MALHA 100% ALGODÃO MANGA LONGA | G18: CAMISETA | H18: LEVE | I18: 45 | J18: 45 | K18: =I18*J18 -> 2025 | L18: 45593 | M18: =IF(L18<TODAY(),"ATRASO","EM PRODUÇÃO") -> ATRASO | O18: OK | P18: OK | Q18: OK | R18: OK | S18: OK | T18: OK | U18: ENTREGUE
A19: DANIELE | B19: 45579 | C19: HAVANNA | D19: 1033 | E19: ZF ALIMENTOS (HAVANNA MARILIA) | F19: BABY LOOK FEMININA MALHA 100% ALGODÃO | G19: CAMISETA | H19: LEVE | I19: =3+3+3+2 -> 11 | J19: 36.75 | K19: =I19*J19 -> 404.25 | L19: 45593 | M19: =IF(L19<TODAY(),"ATRASO","EM PRODUÇÃO") -> ATRASO | N19: 45593 | O19: OK | P19: OK | Q19: OK | R19: OK | S19: OK | T19: 1215 | U19: ENTREGUE
A20: DANIELE | B20: 45579 | C20: HAVANNA | D20: 1033 | E20: ZF ALIMENTOS (HAVANNA MARILIA) | F20: CAMISETA FEMININA MALHA 100% ALGODÃO MANGA LONGA | G20: CAMISETA | H20: LEVE | I20: 8 | J20: 47.5 | K20: =I20*J20 -> 380 | L20: 45593 | M20: =IF(L20<TODAY(),"ATRASO","EM PRODUÇÃO") -> ATRASO | N20: 45593 | O20: OK | P20: OK | Q20: OK | R20: OK | S20: OK | T20: 1215 | U20: ENTREGUE
A21: DANIELE | B21: 45579 | C21: HAVANNA | D21: 1033 | E21: ZF ALIMENTOS (HAVANNA MARILIA) | F21: CAMISETA GOLA CARECA MALHA 100% ALGODÃO | G21: CAMISETA | H21: LEVE | I21: 3 | J21: 36.75 | K21: =I21*J21 -> 110.25 | L21: 45593 | M21: =IF(L21<TODAY(),"ATRASO","EM PRODUÇÃO") -> ATRASO | N21: 45593 | O21: OK | P21: OK | Q21: OK | R21: OK | S21: OK | T21: 1215 | U21: ENTREGUE
A22: DANIELE | B22: 45579 | C22: HAVANNA | D22: 1033 | E22: ZF ALIMENTOS (HAVANNA MARILIA) | F22: CALÇA LEGGIN SUPLEX | G22: CALÇA | H22: LEVE | I22: 12 | J22: 65 | K22: =I22*J22 -> 780 | L22: 45593 | M22: =IF(L22<TODAY(),"ATRASO","EM PRODUÇÃO") -> ATRASO | N22: 45593 | O22: OK | P22: OK | Q22: OK | R22: OK | S22: OK | T22: 1215 | U22: ENTREGUE
A23: DANIELE | B23: 45579 | C23: HAVANNA | D23: 1033 | E23: ZF ALIMENTOS (HAVANNA MARILIA) | F23: FAIXA PARA CABELO TORCIDA | G23: FAIXA | H23: LEVE | I23: 10 | J23: 21 | K23: =I23*J23 -> 210 | L23: 45593 | M23: =IF(L23<TODAY(),"ATRASO","EM PRODUÇÃO") -> ATRASO | N23: 45593 | O23: OK | P23: OK | Q23: OK | R23: OK | S23: OK | T23: 1215 | U23: ENTREGUE
A24: DANIELE | B24: 45579 | C24: HAVANNA | D24: 1033 | E24: ZF ALIMENTOS (HAVANNA MARILIA) | F24: AVENTAL OXFORD MODELO PADRÃO | G24: AVENTAL | H24: LEVE | I24: 10 | J24: 21 | K24: =I24*J24 -> 210 | L24: 45593 | M24: =IF(L24<TODAY(),"ATRASO","EM PRODUÇÃO") -> ATRASO | N24: 45593 | O24: OK | P24: OK | Q24: OK | R24: OK | S24: OK | T24: 1215 | U24: ENTREGUE
A25: LETICIA | B25: 45555 | C25: HAVANNA | D25: 1015 | E25: DOCES E DOCES (HAVANNA PRAIA DE BELLAS) | F25: CAMISETA MALHA 100% ALGODÃO MANGA LONGA | G25: CAMISETA | H25: LEVE | I25: 25 | J25: 45 | K25: =I25*J25 -> 1125 | L25: 45593 | M25: =IF(L25<TODAY(),"ATRASO","EM PRODUÇÃO") -> ATRASO | O25: OK | P25: OK | Q25: OK | R25: OK | S25: OK | T25: OK | U25: ENTREGUE
A26: LETICIA | B26: 45555 | C26: HAVANNA | D26: 1015 | E26: DOCES E DOCES (HAVANNA PRAIA DE BELLAS) | F26: FAIXA PARA CABELO TORCIDA | G26: FAIXA | H26: LEVE | I26: 10 | J26: 21 | K26: =I26*J26 -> 210 | L26: 45593 | M26: =IF(L26<TODAY(),"ATRASO","EM PRODUÇÃO") -> ATRASO | O26: OK | P26: OK | Q26: OK | R26: OK | S26: OK | T26: OK | U26: ENTREGUE
A27: LETICIA | B27: 45560 | C27: PET | D27: 188 | E27: BAMBU BRASIL(ESSENCIA PET) | F27: AVENTAL PET NY IMPERMEAVEL COM VIES | G27: AVENTAL | H27: LEVE | I27: 150 | J27: 23.5 | K27: =I27*J27 -> 3525 | L27: 45583 | M27: =IF(L27<TODAY(),"ATRASO","EM PRODUÇÃO") -> ATRASO | N27: 45588 | O27: OK | P27: OK | Q27: OK | R27: OK | S27: OK | T27: OK | U27: ENTREGUE
A28: LETICIA | B28: 45555 | C28: HAVANNA | D28: 1015 | E28: DOCES E DOCES (HAVANNA PRAIA DE BELLAS) | F28: AVENTAL OXFORD MODELO PADRÃO | G28: AVENTAL | H28: LEVE | I28: 10 | J28: 21 | K28: =I28*J28 -> 210 | L28: 45593 | M28: =IF(L28<TODAY(),"ATRASO","EM PRODUÇÃO") -> ATRASO | O28: OK | P28: OK | Q28: OK | R28: OK | S28: OK | T28: OK | U28: ENTREGUE
A29: DANIELE | B29: 45569 | C29: HAVANNA | D29: 1028 | E29: DRL CAFETERIA (HAVANNA INDAIATUBA) | F29: AVENTAL OXFORD MODELO PADRÃO | G29: AVENTAL | H29: LEVE | I29: 7 | J29: 21 | K29: =I29*J29 -> 147 | L29: 45593 | M29: =IF(L29<TODAY(),"ATRASO","EM PRODUÇÃO") -> ATRASO | O29: OK | P29: OK | Q29: OK | R29: OK | S29: OK | T29: OK | U29: ENTREGUE
A30: DANIELE | B30: 45569 | C30: HAVANNA | D30: 1028 | E30: DRL CAFETERIA (HAVANNA INDAIATUBA) | F30: CAMISETA GOLA CARECA MALHA 100% ALGODÃO | G30: CAMISETA | H30: LEVE | I30: 6 | J30: 41.75 | K30: =I30*J30 -> 250.5 | L30: 45593 | M30: =IF(L30<TODAY(),"ATRASO","EM PRODUÇÃO") -> ATRASO | O30: OK | P30: OK | Q30: OK | R30: OK | S30: OK | T30: OK | U30: ENTREGUE
A31: DANIELE | B31: 45569 | C31: HAVANNA | D31: 1028 | E31: DRL CAFETERIA (HAVANNA INDAIATUBA) | F31: CAMISETA GOLA CARECA MALHA 100% ALGODÃO | G31: CAMISETA | H31: LEVE | I31: 4 | J31: 36.75 | K31: =I31*J31 -> 147 | L31: 45593 | M31: =IF(L31<TODAY(),"ATRASO","EM PRODUÇÃO") -> ATRASO | O31: OK | P31: OK | Q31: OK | R31: OK | S31: OK | T31: OK | U31: ENTREGUE
A32: DANIELE | B32: 45569 | C32: HAVANNA | D32: 1028 | E32: DRL CAFETERIA (HAVANNA INDAIATUBA) | F32: FAIXA PARA CABELO TORCIDA | G32: FAIXA | H32: LEVE | I32: 6 | J32: 21 | K32: =I32*J32 -> 126 | L32: 45593 | M32: =IF(L32<TODAY(),"ATRASO","EM PRODUÇÃO") -> ATRASO | O32: OK | P32: OK | Q32: OK | R32: OK | S32: OK | T32: OK | U32: ENTREGUE
A33: DANIELE | B33: 45589 | C33: HAVANNA | D33: 1022 | E33: JL COMERCIO DE ALIMENTOS (HAVANNA) | F33: FAIXA PARA CABELO TORCIDA | G33: FAIXA | H33: LEVE | I33: 12 | J33: 21 | K33: =I33*J33 -> 252 | L33: 45593 | M33: =IF(L33<TODAY(),"ATRASO","EM PRODUÇÃO") -> ATRASO | N33: 45594 | O33: OK | P33: OK | Q33: OK | R33: OK | S33: OK | T33: 1219 | U33: ENTREGUE
A34: DANIELE | B34: 45589 | C34: HAVANNA | D34: 1022 | E34: JL COMERCIO DE ALIMENTOS (HAVANNA) | F34: CAMISETA FEMININA MALHA 100% ALGODÃO MANGA LONGA | G34: CAMISETA | H34: LEVE | I34: =4+2+2+2 -> 10 | J34: 47.5 | K34: =I34*J34 -> 475 | L34: 45593 | M34: =IF(L34<TODAY(),"ATRASO","EM PRODUÇÃO") -> ATRASO | N34: 45594 | O34: OK | P34: OK | Q34: OK | R34: OK | S34: OK | T34: 1219 | U34: ENTREGUE
A35: DANIELE | B35: 45589 | C35: HAVANNA | D35: 1022 | E35: JL COMERCIO DE ALIMENTOS (HAVANNA) | F35: CAMISETA GOLA CARECA 100% ALGODÃO | G35: CAMISETA | H35: LEVE | I35: =2+2+2 -> 6 | J35: 36.75 | K35: =I35*J35 -> 220.5 | L35: 45593 | M35: =IF(L35<TODAY(),"ATRASO","EM PRODUÇÃO") -> ATRASO | N35: 45594 | O35: OK | P35: OK | Q35: OK | R35: OK | S35: OK | T35: 1219 | U35: ENTREGUE
A36: DANIELE | B36: 45589 | C36: HAVANNA | D36: 1022 | E36: JL COMERCIO DE ALIMENTOS (HAVANNA) | F36: BABY LOOK FEMININA MALHA 100% ALGODÃO | G36: CAMISETA | H36: LEVE | I36: =3+3+3+2 -> 11 | J36: 36.75 | K36: =I36*J36 -> 404.25 | L36: 45593 | M36: =IF(L36<TODAY(),"ATRASO","EM PRODUÇÃO") -> ATRASO | N36: 45594 | O36: OK | P36: OK | Q36: OK | R36: OK | S36: OK | T36: 1219 | U36: ENTREGUE
A37: DANIELE | B37: 45589 | C37: HAVANNA | D37: 1022 | E37: JL COMERCIO DE ALIMENTOS (HAVANNA) | F37: AVENTAL OXFORD MODELO PADRÃO | G37: AVENTAL | H37: LEVE | I37: 13 | J37: 21 | K37: =I37*J37 -> 273 | L37: 45593 | M37: =IF(L37<TODAY(),"ATRASO","EM PRODUÇÃO") -> ATRASO | N37: 45594 | O37: OK | P37: OK | Q37: OK | R37: OK | S37: OK | T37: 1219 | U37: ENTREGUE
A38: LETICIA | B38: 45573 | C38: COSMÉTICO | D38: 617 | E38: M.D BOSO PROHALL | F38: KIMONO CETIM - TAM ÚNICO | G38: KIMONO | H38: LEVE | I38: 400 | J38: 24.5 | K38: =I38*J38 -> 9800 | L38: 45595 | M38: =IF(L38<TODAY(),"ATRASO","EM PRODUÇÃO") -> ATRASO | N38: 45607 | O38: OK | P38: OK | Q38: OK | R38: OK | S38: OK | T38: 967 | U38: ENTREGUE
A39: LETICIA | B39: 45574 | C39: COSMÉTICO | D39: 621 | E39: KOOSMETICS (EXO) | F39: NECESSSAIRE CRISTAL 30A X 16L X 10 - EXO | G39: NECESSAIRE | H39: PESADA | I39: 500 | J39: 7.8 | K39: =I39*J39 -> 3900 | L39: 45595 | M39: =IF(L39<TODAY(),"ATRASO","EM PRODUÇÃO") -> ATRASO | N39: 45594 | O39: OK | P39: OK | Q39: OK | R39: OK | S39: OK | T39: 964 | U39: ENTREGUE
A40: LETICIA | B40: 45573 | C40: COSMÉTICO | D40: 617 | E40: M.D BOSO PROHALL | F40: AVENTAL OXFORD MODELO PADRÃO | G40: AVENTAL | H40: LEVE | I40: =400+300 -> 700 | J40: 14 | K40: =I40*J40 -> 9800 | L40: 45595 | M40: =IF(L40<TODAY(),"ATRASO","EM PRODUÇÃO") -> ATRASO | N40: 45607 | O40: OK | P40: OK | Q40: OK | R40: OK | S40: OK | T40: 967 | U40: ENTREGUE
A41: LETICIA | B41: 45572 | C41: PET | D41: 615 | E41: ECO COSMETICOS | F41: AVENTAL NYLON EMBORRACHADO COR VERDE | G41: AVENTAL | H41: LEVE | I41: 150 | J41: 23 | K41: =I41*J41 -> 3450 | L41: 45600 | M41: =IF(L41<TODAY(),"ATRASO","EM PRODUÇÃO") -> ATRASO | N41: 45600 | O41: OK | P41: OK | Q41: OK | R41: OK | S41: OK | T41: 965 | U41: ENTREGUE
A42: LETICIA | B42: 45572 | C42: PET | D42: 1029 | E42: PET SOCIETY | F42: AVENTAL NYLON EMBORRACHADO CA 45.305-HYDRA | G42: AVENTAL | H42: LEVE | I42: 2500 | J42: 23.5 | K42: =I42*J42 -> 58750 | L42: 45601 | M42: =IF(L42<TODAY(),"ATRASO","EM PRODUÇÃO") -> ATRASO | O42: OK | P42: OK | Q42: OK | R42: OK | S42: OK | T42: OK | U42: ENTREGUE
A43: LETICIA | B43: 45573 | C43: EDITORA | D43: 191 | E43: EDITORA GALERA | F43: SAQUINHO ALGODÃO | G43: SACO | H43: LEVE | I43: 4000 | J43: 5.3 | K43: =I43*J43 -> 21200 | L43: 45601 | M43: =IF(L43<TODAY(),"ATRASO","EM PRODUÇÃO") -> ATRASO | N43: 45596 | O43: OK | P43: OK | Q43: OK | R43: OK | S43: OK | T43: 156 | U43: ENTREGUE
A44: LETICIA | B44: 45569 | C44: COSMÉTICO | D44: 613 | E44: FLORACTIVE | F44: CAMISETA GOLA CARECA MALHA PV | G44: CAMISETA | H44: LEVE | I44: 130 | J44: 16.5 | K44: =I44*J44 -> 2145 | L44: 45602 | M44: =IF(L44<TODAY(),"ATRASO","EM PRODUÇÃO") -> ATRASO | N44: 45608 | O44: OK | P44: OK | Q44: OK | R44: OK | S44: OK | T44: 969 | U44: ENTREGUE
A45: LETICIA | B45: 45574 | C45: COSMÉTICO | D45: 620 | E45: EAE COSMETICOS | F45: CAMISETA GOLA CARECA MALHA PV | G45: CAMISETA | H45: LEVE | I45: 160 | J45: 35 | K45: =I45*J45 -> 5600 | L45: 45602 | M45: =IF(L45<TODAY(),"ATRASO","EM PRODUÇÃO") -> ATRASO | N45: 45602 | O45: OK | P45: OK | Q45: OK | R45: OK | S45: OK | T45: 966 | U45: ENTREGUE
A46: LETICIA | B46: 45574 | C46: INDUSTRIA | D46: 192 | E46: GIRARDI CONFECCAO | F46: CAMISETA GOLA CARECA MALHA PV | G46: CAMISETA | H46: LEVE | I46: 80 | J46: 26.5 | K46: =I46*J46 -> 2120 | L46: 45602 | M46: =IF(L46<TODAY(),"ATRASO","EM PRODUÇÃO") -> ATRASO | N46: 45607 | O46: OK | P46: OK | Q46: OK | R46: OK | S46: OK | T46: OK | U46: ENTREGUE
A47: LETICIA | B47: 45574 | C47: INDUSTRIA | D47: 193 | E47: GIRARDI CONFECCAO | F47: CAMISETA GOLA CARECA MALHA PV | G47: CAMISETA | H47: LEVE | I47: 80 | J47: 26.5 | K47: =I47*J47 -> 2120 | L47: 45603 | M47: =IF(L47<TODAY(),"ATRASO","EM PRODUÇÃO") -> ATRASO | N47: 45607 | O47: OK | P47: OK | Q47: OK | R47: OK | S47: OK | T47: OK | U47: ENTREGUE
A48: DANIELE | B48: 45540 | C48: PET | D48: 194 | E48: MANU PET STORE | F48: AVENTAL PET NY IMPERMEAVEL COM VIES | G48: AVENTAL | H48: LEVE | I48: 100 | J48: 27 | K48: =I48*J48 -> 2700 | L48: 45603 | M48: =IF(L48<TODAY(),"ATRASO","EM PRODUÇÃO") -> ATRASO | O48: OK | P48: OK | Q48: OK | R48: OK | S48: OK | T48: OK | U48: ENTREGUE
A49: LETICIA | B49: 45579 | C49: BARBEARIA | D49: 197 | E49: DONA NAVALHA BARBEARIA | F49: CAPA DE CORTE TACTEL | G49: CAPA | H49: LEVE | I49: 20 | J49: 80 | K49: =I49*J49 -> 1600 | L49: 45604 | M49: =IF(L49<TODAY(),"ATRASO","EM PRODUÇÃO") -> ATRASO | N49: 45607 | O49: OK | P49: OK | Q49: OK | R49: OK | S49: OK | T49: OK | U49: ENTREGUE
A50: LETICIA | B50: 45576 | C50: COSMÉTICO | D50: 195 | E50: GABONI | F50: AVENTAL SEMI IMPERMEAVEL | G50: AVENTAL | H50: LEVE | I50: 100 | J50: 19.5 | K50: =I50*J50 -> 1950 | L50: 45604 | M50: =IF(L50<TODAY(),"ATRASO","EM PRODUÇÃO") -> ATRASO | N50: 45603 | O50: OK | P50: OK | Q50: OK | R50: OK | S50: OK | T50: 161 | U50: ENTREGUE
A51: LETICIA | B51: 45579 | C51: INDUSTRIA | D51: 1041 | E51: NESTING | F51: ETIQUETA ALGODÃO CRU | G51: ETIQUETA | H51: LEVE | I51: 500 | J51: 2.5 | K51: =I51*J51 -> 1250 | L51: 45607 | M51: =IF(L51<TODAY(),"ATRASO","EM PRODUÇÃO") -> ATRASO | O51: OK | P51: OK | Q51: OK | R51: OK | S51: OK | T51: OK | U51: ENTREGUE
A52: LETICIA | B52: 45580 | C52: INDUSTRIA | D52: 1034 | E52: PLATOLANDIA | F52: CAMISETA GOLA CARECA 100% ALGODÃO | G52: CAMISETA | H52: LEVE | I52: 200 | J52: 26.19 | K52: =I52*J52 -> 5238 | L52: 45608 | M52: =IF(L52<TODAY(),"ATRASO","EM PRODUÇÃO") -> ATRASO | O52: OK | P52: OK | Q52: OK | R52: OK | S52: OK | T52: OK | U52: ENTREGUE
A53: LETICIA | B53: 45581 | C53: COSMÉTICO | D53: 198 | E53: DUO INDUSTRIA (KPRO) | F53: AVENTAL NY EMBORRACHADO 5 BOLSOS | G53: AVENTAL | H53: LEVE | I53: 300 | J53: 19.2 | K53: =I53*J53 -> 5760 | L53: 45609 | M53: =IF(L53<TODAY(),"ATRASO","EM PRODUÇÃO") -> ATRASO | N53: 45614 | O53: OK | P53: OK | Q53: OK | R53: OK | S53: OK | T53: 168 | U53: ENTREGUE
A54: LETICIA | B54: 45582 | C54: PET | D54: 622 | E54: LDM PELONCIO PET | F54: AVENTAL PET NY IMPERMEAVEL COM VIES | G54: AVENTAL | H54: LEVE | I54: 250 | J54: 21.5 | K54: =I54*J54 -> 5375 | L54: 45609 | M54: =IF(L54<TODAY(),"ATRASO","EM PRODUÇÃO") -> ATRASO | N54: 45607 | O54: OK | P54: OK | Q54: OK | R54: OK | S54: OK | T54: 968 | U54: ENTREGUE
A55: LETICIA | B55: 45582 | C55: COSMÉTICO | D55: 623 | E55: HRT COSMETICOS (MERLOT) | F55: AVENTAL OXFORD MODELO PADRÃO | G55: AVENTAL | H55: LEVE | I55: 100 | J55: 17.5 | K55: =I55*J55 -> 1750 | L55: 45610 | M55: =IF(L55<TODAY(),"ATRASO","EM PRODUÇÃO") -> ATRASO | N55: 45614 | O55: OK | P55: OK | Q55: OK | R55: OK | S55: OK | T55: 971 | U55: ENTREGUE
A56: LETICIA | B56: 45582 | C56: COSMÉTICO | D56: 623 | E56: HRT COSMETICOS (MERLOT) | F56: CAPA DE CORTE CETIM 0,85 X 1,40 | G56: CAPA | H56: LEVE | I56: 100 | J56: 18.5 | K56: =I56*J56 -> 1850 | L56: 45610 | M56: =IF(L56<TODAY(),"ATRASO","EM PRODUÇÃO") -> ATRASO | N56: 45614 | O56: OK | P56: OK | Q56: OK | R56: OK | S56: OK | T56: 971 | U56: ENTREGUE
A57: LETICIA | B57: 45583 | C57: PET | D57: 201 | E57: PETNOR | F57: AVENTAL PET NY IMPERMEAVEL COM VIES | G57: AVENTAL | H57: LEVE | I57: 200 | J57: 22.5 | K57: =I57*J57 -> 4500 | L57: 45610 | M57: =IF(L57<TODAY(),"ATRASO","EM PRODUÇÃO") -> ATRASO | N57: 45618 | O57: OK | P57: OK | Q57: OK | R57: OK | S57: OK | T57: 174 | U57: ENTREGUE
A58: LETICIA | B58: 45582 | C58: COSMÉTICO | D58: 199 | E58: FLORACTIVE | F58: AVENTAL VINTAGE | G58: AVENTAL | H58: PESADA | I58: 100 | J58: 60 | K58: =I58*J58 -> 6000 | L58: 45610 | M58: =IF(L58<TODAY(),"ATRASO","EM PRODUÇÃO") -> ATRASO | N58: 45608 | O58: OK | P58: OK | Q58: OK | R58: OK | S58: OK | T58: 166 | U58: ENTREGUE
A59: LETICIA | B59: 45611 | C59: COSMÉTICO | D59: 200 | E59: MUNDIAL COSMETICOS | F59: NECESSAIRE MALETA | G59: NECESSAIRE | H59: PESADA | I59: 100 | J59: 20 | K59: =I59*J59 -> 2000 | L59: 45611 | M59: =IF(L59<TODAY(),"ATRASO","EM PRODUÇÃO") -> ATRASO | N59: 45615 | O59: OK | P59: OK | Q59: OK | R59: OK | S59: OK | T59: 169 | U59: ENTREGUE
A60: LETICIA | B60: 45586 | C60: INDUSTRIA | D60: 624 | E60: VOICER STORE COMERCIO E SERVIÇOS | F60: NECESSAIRE NY PLASTIFICADO PEQUENA 22L X 17A X 5 | G60: NECESSAIRE | H60: PESADA | I60: 500 | J60: 23 | K60: =I60*J60 -> 11500 | L60: 45614 | M60: =IF(L60<TODAY(),"ATRASO","EM PRODUÇÃO") -> ATRASO | N60: 45614 | O60: OK | P60: OK | Q60: OK | R60: OK | S60: OK | T60: 972 | U60: ENTREGUE
A61: LETICIA | B61: 45586 | C61: INDUSTRIA | D61: 624 | E61: VOICER STORE COMERCIO E SERVIÇOS | F61: NECESSAIRE NY PLASTIFICADO GRANDE 26L X 20A X 9 | G61: NECESSAIRE | H61: PESADA | I61: 200 | J61: 23 | K61: =I61*J61 -> 4600 | L61: 45614 | M61: =IF(L61<TODAY(),"ATRASO","EM PRODUÇÃO") -> ATRASO | N61: 45614 | O61: OK | P61: OK | Q61: OK | R61: OK | S61: OK | T61: 972 | U61: ENTREGUE
A62: LETICIA | B62: 45582 | C62: COSMÉTICO | D62: 204 | E62: VAI VIVER | F62: SAQUINHO ALGODÃO | G62: SACO | H62: LEVE | I62: 300 | J62: 7.1 | K62: =I62*J62 -> 2130 | L62: 45615 | M62: =IF(L62<TODAY(),"ATRASO","EM PRODUÇÃO") -> ATRASO | N62: FALTA MATERIAL | O62: OK | P62: OK | Q62: OK | R62: OK | S62: OK | T62: 167 | U62: ENTREGUE
A63: LETICIA | B63: 45582 | C63: COSMÉTICO | D63: 204 | E63: VAI VIVER | F63: NECESSAIRE NYLON PLASTIFICADO COM ZIPER | G63: NECESSAIRE | H63: PESADA | I63: 200 | J63: 13.5 | K63: =I63*J63 -> 2700 | L63: 45615 | M63: =IF(L63<TODAY(),"ATRASO","EM PRODUÇÃO") -> ATRASO | N63: FALTA MATERIAL | O63: OK | P63: OK | Q63: OK | R63: OK | S63: OK | T63: 167 | U63: ENTREGUE
A64: LETICIA | B64: 45582 | C64: COSMÉTICO | D64: 204 | E64: VAI VIVER | F64: NECESSAIRE NYLON PLASTIFICADO COM ZIPER | G64: NECESSAIRE | H64: PESADA | I64: 200 | J64: 13.5 | K64: =I64*J64 -> 2700 | L64: 45615 | M64: =IF(L64<TODAY(),"ATRASO","EM PRODUÇÃO") -> ATRASO | N64: FALTA MATERIAL | O64: OK | P64: OK | Q64: OK | R64: OK | S64: OK | T64: 167 | U64: ENTREGUE
A65: LETICIA | B65: 45582 | C65: COSMÉTICO | D65: 204 | E65: VAI VIVER | F65: SACOCHILA NYLON EMBORRACHADO | G65: SACO | H65: LEVE | I65: 200 | J65: 12 | K65: =I65*J65 -> 2400 | L65: 45615 | M65: =IF(L65<TODAY(),"ATRASO","EM PRODUÇÃO") -> ATRASO | N65: FALTA MATERIAL | O65: OK | P65: OK | Q65: OK | R65: OK | S65: OK | T65: 167 | U65: ENTREGUE
A66: LETICIA | B66: 45582 | C66: COSMÉTICO | D66: 204 | E66: VAI VIVER | F66: SACOCHILA NYLON EMBORRACHADO | G66: SACO | H66: LEVE | I66: 200 | J66: 12 | K66: =I66*J66 -> 2400 | L66: 45615 | M66: =IF(L66<TODAY(),"ATRASO","EM PRODUÇÃO") -> ATRASO | N66: FALTA MATERIAL | O66: OK | P66: OK | Q66: OK | R66: OK | S66: OK | T66: 167 | U66: ENTREGUE
A67: LETICIA | B67: 45587 | C67: PET | D67: 1041 | E67: DOLCE PET (SOLUTION) | F67: AVENTAL PET NY IMPERMEAVEL COM VIES | G67: AVENTAL | H67: LEVE | I67: 400 | J67: 20 | K67: =I67*J67 -> 8000 | L67: 45615 | M67: =IF(L67<TODAY(),"ATRASO","EM PRODUÇÃO") -> ATRASO | N67: 45614 | O67: OK | P67: OK | Q67: OK | R67: OK | S67: OK | T67: 1228 | U67: ENTREGUE
A68: LETICIA | B68: 45642 | C68: PET | D68: 658 | E68: LDM PELONCIO PET | F68: JALECO GROOMER MICROFIBRA | G68: JALECO | H68: LEVE | I68: 50 | J68: 40 | K68: =I68*J68 -> 2000 | L68: 45308 | M68: =IF(L68<TODAY(),"ATRASO","EM PRODUÇÃO") -> ATRASO
A69: LETICIA | B69: 45590 | C69: COSMÉTICO | D69: 203 | E69: A GILISE COSMETICOS | F69: CAPA DE CETIM 0,85 X 1,40 | G69: CAPA | H69: LEVE | I69: 50 | J69: 20 | K69: =I69*J69 -> 1000 | L69: 45618 | M69: =IF(L69<TODAY(),"ATRASO","EM PRODUÇÃO") -> ATRASO | N69: 45617 | O69: OK | P69: OK | Q69: OK | R69: OK | S69: OK | T69: 170 | U69: ENTREGUE
A70: LETICIA | B70: 45594 | C70: COSMÉTICO | D70: 211 | E70: LUNIX COMERCIO | F70: AVENTAL SEMI IMPERMEAVEL | G70: AVENTAL | H70: LEVE | I70: 50 | J70: 23.5 | K70: =I70*J70 -> 1175 | L70: 45618 | M70: =IF(L70<TODAY(),"ATRASO","EM PRODUÇÃO") -> ATRASO | N70: 45622 | O70: OK | P70: OK | Q70: OK | R70: OK | S70: OK | T70: OK | U70: ENTREGUE
A71: LETICIA | B71: 45595 | C71: PET | D71: 626 | E71: BUBBLES PETS | F71: AVENTAL PET NY IMPERMEAVEL COM VIES | G71: AVENTAL | H71: LEVE | I71: 200 | J71: 21.5 | K71: =I71*J71 -> 4300 | L71: 45621 | M71: =IF(L71<TODAY(),"ATRASO","EM PRODUÇÃO") -> ATRASO | N71: 45618 | O71: ok | P71: ok | Q71: ok | R71: OK | S71: OK | T71: 975 | U71: ENTREGUE
A72: LETICIA | B72: 45594 | C72: COSMÉTICO | D72: 211 | E72: LUNIX COMERCIO | F72: CAPA DE CORTE 1,40 X 1,50 | G72: CAPA | H72: LEVE | I72: 100 | J72: 26.5 | K72: =I72*J72 -> 2650 | L72: 45618 | M72: =IF(L72<TODAY(),"ATRASO","EM PRODUÇÃO") -> ATRASO | N72: 45622 | O72: OK | P72: OK | Q72: OK | R72: OK | S72: OK | T72: OK | U72: ENTREGUE
A73: LETICIA | B73: 45593 | C73: COSMÉTICO | D73: 1045 | E73: DAVENNE | F73: XUXINHA DE CETIM | G73: XUXINHA | H73: LEVE | I73: 1000 | J73: 4 | K73: =I73*J73 -> 4000 | L73: 45621 | M73: =IF(L73<TODAY(),"ATRASO","EM PRODUÇÃO") -> ATRASO | N73: 45643 | O73: OK | P73: OK | Q73: OK | R73: OK | S73: OK | T73: 1263 | U73: ENTREGUE
A74: LETICIA | B74: 45594 | C74: INDUSTRIA | D74: 627 | E74: MARCEARIA (MUSKINHA) | F74: SACO ALGODAO | G74: SACO | H74: LEVE | I74: 400 | J74: 8.5 | K74: =I74*J74 -> 3400 | L74: 45625 | M74: =IF(L74<TODAY(),"ATRASO","EM PRODUÇÃO") -> ATRASO | O74: OK | P74: OK | Q74: OK | R74: OK | S74: OK | T74: OK | U74: ENTREGUE
A75: LETICIA | B75: 45591 | C75: COSMÉTICO | D75: 1043 | E75: KOOSMETICS (EXO) | F75: CAPA DE CORTE TACTEL | G75: CAPA | H75: LEVE | I75: 300 | J75: 18 | K75: =I75*J75 -> 5400 | L75: 45622 | M75: =IF(L75<TODAY(),"ATRASO","EM PRODUÇÃO") -> ATRASO | N75: 45623 | O75: OK | P75: OK | Q75: OK | R75: OK | S75: OK | T75: OK | U75: ENTREGUE
A76: LETICIA | B76: 45614 | C76: AGENCIA | D76: 1060 | E76: BEM RUBENS AGENCIA FAR | F76: LENÇO SUBLIMADO | G76: LENÇO | H76: LEVE | I76: 4 | J76: 100 | K76: =I76*J76 -> 400 | L76: 45624 | M76: =IF(L76<TODAY(),"ATRASO","EM PRODUÇÃO") -> ATRASO | N76: 45624 | O76: OK | P76: OK | Q76: OK | R76: OK | S76: OK | T76: OK | U76: ENTREGUE
A77: LETICIA | B77: 45587 | C77: PET | D77: 1041 | E77: SOLUTION DISTRIBUIDORA | F77: AVENTAL PET NY IMPERMEAVEL COM VIES | G77: AVENTAL | H77: LEVE | I77: 400 | J77: 20 | K77: =I77*J77 -> 8000 | L77: 45615 | M77: =IF(L77<TODAY(),"ATRASO","EM PRODUÇÃO") -> ATRASO | N77: 45617 | O77: OK | P77: OK | Q77: OK | R77: OK | S77: OK | T77: 1232 | U77: ENTREGUE
A78: LETICIA | B78: 45593 | C78: INDUSTRIA | D78: 205 | E78: MER MARIA SUBLIME | F78: SAQUINHO ALGODÃO | G78: SACO | H78: LEVE | I78: 500 | J78: 3.15 | K78: =I78*J78 -> 1575 | L78: 45624 | M78: =IF(L78<TODAY(),"ATRASO","EM PRODUÇÃO") -> ATRASO | O78: OK | P78: OK | Q78: OK | R78: OK | S78: OK | T78: OK | U78: ENTREGUE
A79: LETICIA | B79: 45594 | C79: COSMÉTICO | D79: 211 | E79: LUNIX COMERCIO | F79: NECESSAIRE NY 600 L | G79: NECESSAIRE | H79: PESADA | I79: 1000 | J79: 7.4 | K79: =I79*J79 -> 7400 | L79: 45618 | M79: =IF(L79<TODAY(),"ATRASO","EM PRODUÇÃO") -> ATRASO | N79: 45622 | O79: OK | P79: OK | Q79: OK | R79: OK | S79: OK | T79: OK | U79: ENTREGUE
A80: LETICIA | B80: 45594 | C80: COSMÉTICO | D80: 207 | E80: LORENA CARVALHO | F80: CAPA DE CORTE DE CETIM | G80: CAPA | H80: LEVE | I80: 100 | J80: 28 | K80: =I80*J80 -> 2800 | L80: 45625 | M80: =IF(L80<TODAY(),"ATRASO","EM PRODUÇÃO") -> ATRASO | N80: 45622 | O80: OK | P80: OK | Q80: OK | R80: OK | S80: OK | T80: OK | U80: ENTREGUE
A81: DANIELE | B81: 45597 | C81: COSMÉTICO | D81: 207 | E81: LORENA CARVALHO | F81: AVENTAL SEMI IMPERMEAVEL | G81: AVENTAL | H81: LEVE | I81: 100 | J81: 19.7 | K81: =I81*J81 -> 1970 | L81: 45625 | M81: =IF(L81<TODAY(),"ATRASO","EM PRODUÇÃO") -> ATRASO | N81: 45622 | O81: OK | P81: OK | Q81: OK | R81: OK | S81: OK | T81: OK | U81: ENTREGUE
A82: LETICIA | B82: 45594 | C82: INDUSTRIA | D82: 206 | E82: TAPIS | F82: SACO ALGODAO | G82: SACO | H82: LEVE | I82: 200 | J82: 15.5 | K82: =I82*J82 -> 3100 | L82: 45625 | M82: =IF(L82<TODAY(),"ATRASO","EM PRODUÇÃO") -> ATRASO | N82: 45618 | O82: OK | P82: OK | Q82: OK | R82: OK | S82: OK | T82: OK | U82: ENTREGUE
A83: LETICIA | B83: 45572 | C83: PET | D83: 1049 | E83: PET SOCIETY | F83: AVENTAL NYLON EMBORRACHADO CA 45.305-HYDRA | G83: AVENTAL | H83: LEVE | I83: 2500 | J83: 23.5 | K83: =I83*J83 -> 58750 | L83: 45631 | M83: =IF(L83<TODAY(),"ATRASO","EM PRODUÇÃO") -> ATRASO | N83: 45628 | O83: OK | P83: OK | Q83: OK | R83: OK | S83: OK | T83: OK | U83: ENTREGUE
A84: LETICIA | B84: 45600 | C84: BANCO | D84: 628 | E84: SKYCRED SECURITIZADORA | F84: NECESSAIRE CRISTAL COM VIES | G84: NECESSAIRE | H84: PESADA | I84: 100 | J84: 12 | K84: =I84*J84 -> 1200 | L84: 45630 | M84: =IF(L84<TODAY(),"ATRASO","EM PRODUÇÃO") -> ATRASO | N84: 45618 | O84: OK | P84: OK | Q84: OK | R84: OK | S84: OK | T84: 974 | U84: ENTREGUE
A85: LETICIA | B85: 45600 | C85: BANCO | D85: 628 | E85: SKYCRED SECURITIZADORA | F85: SACOLA ALGODÃO | G85: SACOLA | H85: LEVE | I85: 100 | J85: 13 | K85: =I85*J85 -> 1300 | L85: 45630 | M85: =IF(L85<TODAY(),"ATRASO","EM PRODUÇÃO") -> ATRASO | N85: 45618 | O85: OK | P85: OK | Q85: OK | R85: OK | S85: OK | T85: 974 | U85: ENTREGUE
A86: LETICIA | B86: 45615 | C86: PET | D86: 217 | E86: EVOLVE NUTRIÇÃO | F86: CAMISETA POLO MALHA PIQUET | G86: CAMISETA | H86: LEVE | I86: 10 | J86: 65 | K86: =I86*J86 -> 650 | L86: 45625 | M86: =IF(L86<TODAY(),"ATRASO","EM PRODUÇÃO") -> ATRASO | N86: 45625 | O86: OK | P86: OK | Q86: OK | R86: OK | S86: OK | T86: OK | U86: ENTREGUE
A87: LETICIA | B87: 45235 | C87: COSMÉTICO | D87: 210 | E87: JM COSMETICOS LTDA | F87: KIMONO CETIM - TAM ÚNICO | G87: KIMONO | H87: LEVE | I87: 100 | J87: 27.5 | K87: =I87*J87 -> 2750 | L87: 45631 | M87: =IF(L87<TODAY(),"ATRASO","EM PRODUÇÃO") -> ATRASO | N87: 45637 | O87: OK | P87: OK | Q87: OK | R87: OK | S87: OK | T87: OK | U87: ENTREGUE
A88: LETICIA | B88: 45603 | C88: PET | D88: 1054 | E88: PET SOCIETY | F88: CAMISETA GOLA CARECA | G88: CAMISETA | H88: LEVE | I88: 100 | J88: 28 | K88: =I88*J88 -> 2800 | L88: 45635 | M88: =IF(L88<TODAY(),"ATRASO","EM PRODUÇÃO") -> ATRASO | N88: 45628 | O88: OK | P88: OK | Q88: OK | R88: OK | S88: OK | T88: OK | U88: ENTREGUE
A89: LETICIA | B89: 45601 | C89: COSMÉTICO | D89: 209 | E89: FLORACTIVE | F89: TOUCA DE CETIM COM DIFUSOR | G89: TOUCA | H89: LEVE | I89: 500 | J89: 15.5 | K89: =I89*J89 -> 7750 | L89: 45631 | M89: =IF(L89<TODAY(),"ATRASO","EM PRODUÇÃO") -> ATRASO | N89: 45631 | O89: OK | P89: OK | Q89: OK | R89: OK | S89: OK | T89: OK | U89: ENTREGUE
A90: LETICIA | B90: 45603 | C90: COSMÉTICO | D90: 212 | E90: DUO INDUSTRIA (KPRO) | F90: AVENTAL NY EMBORRACHADO 5 BOLSOS | G90: AVENTAL | H90: LEVE | I90: 200 | J90: 19.5 | K90: =I90*J90 -> 3900 | L90: 45635 | M90: =IF(L90<TODAY(),"ATRASO","EM PRODUÇÃO") -> ATRASO | N90: 45635 | O90: OK | P90: OK | Q90: OK | R90: OK | S90: OK | T90: OK | U90: ENTREGUE
A91: LETICIA | B91: 45572 | C91: PET | D91: 631 | E91: ECO COSMETICOS | F91: AVENTAL NYLON EMBORRACHADO | G91: AVENTAL | H91: LEVE | I91: 150 | J91: 23 | K91: =I91*J91 -> 3450 | L91: 45637 | M91: =IF(L91<TODAY(),"ATRASO","EM PRODUÇÃO") -> ATRASO | N91: 45324 | O91: OK | P91: OK | Q91: OK | R91: OK | S91: OK | T91: OK | U91: ENTREGUE
A92: LETICIA | B92: 45582 | C92: PET | D92: 630 | E92: LDM PELONCIO PET | F92: AVENTAL PET NY IMPERMEAVEL COM VIES | G92: AVENTAL | H92: LEVE | I92: 250 | J92: 21.5 | K92: =I92*J92 -> 5375 | L92: 45637 | M92: =IF(L92<TODAY(),"ATRASO","EM PRODUÇÃO") -> ATRASO | N92: 45324 | O92: OK | P92: OK | Q92: OK | R92: OK | S92: OK | T92: 977 | U92: ENTREGUE
A93: LETICIA | B93: 45604 | C93: COSMÉTICO | D93: 215 | E93: DUO INDUSTRIA (KPRO) | F93: CAPA DE CORTE TACTEL | G93: AVENTAL | H93: LEVE | I93: 300 | J93: 28 | K93: =I93*J93 -> 8400 | L93: 45636 | M93: =IF(L93<TODAY(),"ATRASO","EM PRODUÇÃO") -> ATRASO | N93: 45636 | O93: OK | P93: OK | Q93: OK | R93: OK | S93: OK | T93: OK | U93: ENTREGUE
A94: LETICIA | B94: 45608 | C94: COSMÉTICO | D94: 214 | E94: NB COSMÉTICOS (D BIANCO) | F94: AVENTAL IMPERMEAVEL NYEMB MODELO PADRAO | G94: AVENTAL | H94: LEVE | I94: 100 | J94: 23.5 | K94: =I94*J94 -> 2350 | L94: 45638 | M94: =IF(L94<TODAY(),"ATRASO","EM PRODUÇÃO") -> ATRASO | N94: 45636 | O94: OK | P94: OK | Q94: OK | R94: OK | S94: OK | T94: OK | U94: ENTREGUE
A95: LETICIA | B95: 45609 | C95: INDUSTRIA | D95: 632 | E95: MARCEARIA (MUSKINHA) | F95: SACO ALGODAO | G95: SACO | H95: LEVE | I95: 100 | J95: 16.5 | K95: =I95*J95 -> 1650 | L95: 45639 | M95: =IF(L95<TODAY(),"ATRASO","EM PRODUÇÃO") -> ATRASO | N95: 45324 | O95: OK | P95: OK | Q95: OK | R95: OK | S95: OK | T95: OK | U95: ENTREGUE
A96: LETICIA | B96: 45610 | C96: COSMÉTICO | D96: 1059 | E96: TRICOSMETICOS | F96: AVENTAL SUBLIMADO | G96: AVENTAL | H96: LEVE | I96: 300 | J96: 28 | K96: =I96*J96 -> 8400 | L96: 45642 | M96: =IF(L96<TODAY(),"ATRASO","EM PRODUÇÃO") -> ATRASO | N96: 45638 | O96: OK | P96: OK | Q96: OK | R96: OK | S96: OK | T96: 1253 | U96: ENTREGUE
A97: LETICIA | B97: 45608 | C97: COSMÉTICO | D97: 214 | E97: NB COSMÉTICOS (D BIANCO) | F97: CAPA DE CORTE CETIM 1,40 X 1,50 | G97: CAPA | H97: LEVE | I97: 100 | J97: 24.5 | K97: =I97*J97 -> 2450 | L97: 45638 | M97: =IF(L97<TODAY(),"ATRASO","EM PRODUÇÃO") -> ATRASO | N97: 45636 | O97: OK | P97: OK | Q97: OK | R97: OK | S97: OK | T97: OK | U97: ENTREGUE
A98: LETICIA | B98: 45623 | C98: COSMÉTICO | D98: 638 | E98: ROBERTO LAURIZEN (GLAMOURAMA) | F98: AVENTAL OXFORD PADRAO COM GRAVAÇÃO EM SILK SCREEN | G98: AVENTAL | H98: LEVE | I98: 100 | J98: 16 | K98: =I98*J98 -> 1600 | L98: 45642 | M98: =IF(L98<TODAY(),"ATRASO","EM PRODUÇÃO") -> ATRASO
A99: LETICIA | B99: 45614 | C99: COSMÉTICO | D99: 216 | E99: SENHOR BARBA COSMETICOS | F99: NECESSAIRE NYLON PLASTIFICADO COM ZIPER | G99: NECESSAIRE | H99: PESADA | I99: 100 | J99: 17.7 | K99: =I99*J99 -> 1770 | L99: 45643 | M99: =IF(L99<TODAY(),"ATRASO","EM PRODUÇÃO") -> ATRASO | N99: PARCIAL | O99: OK | P99: OK | Q99: OK | R99: OK | S99: OK | T99: OK | U99: ENTREGUE
A100: LETICIA | B100: 45588 | C100: COSMÉTICO | D100: 202 | E100: GALDINO E SENA (KIEV) | F100: CAMISETA MALHA PV GOLA CARECA | G100: CAMISETA | H100: LEVE | I100: 100 | J100: 24.5 | K100: =I100*J100 -> 2450 | L100: 45616 | M100: =IF(L100<TODAY(),"ATRASO","EM PRODUÇÃO") -> ATRASO | N100: 45617 | O100: OK | P100: OK | Q100: OK | R100: OK | S100: OK | T100: 171 | U100: ENTREGUE
...

Sheet Planilha2
A1: VENDEDOR | B1: DATA DE ENTRADA | C1: GRUPO DE CLIENTE | D1: PEDIDO | E1: CLIENTE | F1: PRODUTO | G1: GRUPO | H1: LINHA | I1: QUANTIDADE | J1: PREÇO UNITARIO | K1: TOTAL | L1: DATA DE ENTREGA | M1: CORTE | N1: SILK | O1: COSTURA | P1: EMBALAGEM | Q1: TOTAL MO
A2: LETICIA | B2: 45552 | C2: PET | D2: 176 | E2: PETCO CLEAN & CARE (PETCO) | F2: CAMISETA POLO MALHA PIQUET | G2: CAMISETA | H2: LEVE | I2: 10 | J2: 75 | K2: 750 | L2: 45580 | M2: =I2*0.25 -> 2.5 | O2: =I2*7 -> 70 | P2: =I2*0.5 -> 5 | Q2: =M2+N2+O2+P2 -> 77.5
A3: LETICIA | B3: 45552 | C3: PET | D3: 177 | E3: PETCO CLEAN & CARE (PETCO) | F3: JALECO MICROFIBRA COM TAFETA- PETCO | G3: JALECO | H3: LEVE | I3: 210 | J3: 55 | K3: 11550 | L3: 45580 | M3: =I3*0.25 -> 52.5 | N3: =I3*2 -> 420 | O3: =I3*10 -> 2100 | P3: =I3*0.5 -> 105 | Q3: =M3+N3+O3+P3 -> 2677.5
A4: LETICIA | B4: 45553 | C4: PET | D4: 181 | E4: CHEMVET (PETSPA) | F4: JALECO MICROFIBRA COM TAFETA- PETSPA | G4: JALECO | H4: LEVE | I4: 200 | J4: 55 | K4: 11000 | L4: 45581 | M4: =I4*0.25 -> 50 | N4: =I4*2 -> 400 | O4: =I4*10 -> 2000 | P4: =I4*0.5 -> 100 | Q4: =M4+N4+O4+P4 -> 2550
A5: LETICIA | B5: 45560 | C5: COSMÉTICO | D5: 187 | E5: DUO INDUSTRIA (KPRO) | F5: AVENTAL GABARDINE MODELO PADRÃO | G5: AVENTAL | H5: LEVE | I5: 500 | J5: 19.5 | K5: 9750 | L5: 45588 | M5: =I5*0.25 -> 125 | N5: =I5*0.7 -> 350 | O5: =I5*1.2 -> 600 | P5: =I5*0.5 -> 250 | Q5: =M5+N5+O5+P5 -> 1325
A6: LETICIA | B6: 45572 | C6: COSMÉTICO | D6: 616 | E6: FLORA DISTRIBUIDORA | F6: CAMISETA MALHA PV GOLA CARECA | G6: CAMISETA | H6: LEVE | I6: 112 | J6: 26.5 | K6: 2968 | L6: 45586 | M6: =I6*0.25 -> 28 | N6: =I6*1.5 -> 168 | O6: =I6*1.5 -> 168 | P6: =I6*0.5 -> 56 | Q6: =M6+N6+O6+P6 -> 420
A7: LETICIA | B7: 45581 | C7: COSMÉTICO | D7: 198 | E7: DUO INDUSTRIA (KPRO) | F7: AVENTAL NY EMBORRACHADO 5 BOLSOS | G7: AVENTAL | H7: LEVE | I7: 300 | J7: 19.2 | K7: 5760 | L7: 45609 | M7: =I7*0.25 -> 75 | N7: =I7*0.7 -> 210 | O7: =I7*1.3 -> 390 | P7: =I7*0.5 -> 150 | Q7: =M7+N7+O7+P7 -> 825
A8: LETICIA | B8: 45574 | C8: COSMÉTICO | D8: 619 | E8: M.D BOSO PROHALL | F8: CAMISETA GOLA CARECA MALHA PV | G8: CAMISETA | H8: LEVE | I8: 34 | J8: 24.5 | K8: 833 | L8: 45590 | M8: =I8*0.25 -> 8.5 | N8: =I8*1.5 -> 51 | O8: =I8*1.5 -> 51 | P8: =I8*0.5 -> 17 | Q8: =M8+N8+O8+P8 -> 127.5
A9: LETICIA | B9: 45572 | C9: PET | D9: 1029 | E9: PET SOCIETY | F9: AVENTAL NYLON EMBORRACHADO CA 45.305-HYDRA | G9: AVENTAL | H9: LEVE | I9: 2500 | J9: 23.5 | K9: 58750 | L9: 45601 | M9: =I9*0.25 -> 625 | N9: =I9*1 -> 2500 | O9: =I9*1.65 -> 4125 | P9: =I9*0.5 -> 1250 | Q9: =M9+N9+O9+P9 -> 8500
A10: DANIELE | B10: 45579 | C10: HAVANNA | D10: 1033 | E10: ZF ALIMENTOS (HAVANNA MARILIA) | F10: BABY LOOK FEMININA MALHA 100% ALGODÃO | G10: CAMISETA | H10: LEVE | I10: 11 | J10: 36.75 | K10: 404.25 | L10: 45593 | M10: =I10*0.25 -> 2.75 | N10: =I10*1.5 -> 16.5 | O10: =I10*1.5 -> 16.5 | P10: =I10*0.5 -> 5.5 | Q10: =M10+N10+O10+P10 -> 41.25
A11: LETICIA | B11: 45572 | C11: PET | D11: 615 | E11: ECO COSMETICOS | F11: AVENTAL NYLON EMBORRACHADO COR VERDE | G11: AVENTAL | H11: LEVE | I11: 150 | J11: 23 | K11: 3450 | L11: 45600 | M11: =I11*0.25 -> 37.5 | N11: =I11*1 -> 150 | O11: =I11*1 -> 150 | P11: =I11*0.5 -> 75 | Q11: =M11+N11+O11+P11 -> 412.5
A12: DANIELE | B12: 45589 | C12: HAVANNA | D12: 1022 | E12: JL COMERCIO DE ALIMENTOS (HAVANNA) | F12: BABY LOOK FEMININA MALHA 100% ALGODÃO | G12: CAMISETA | H12: LEVE | I12: 11 | J12: 36.75 | K12: 404.25 | L12: 45593 | M12: =I12*0.25 -> 2.75 | N12: =I12*1.5 -> 16.5 | O12: =I12*1.5 -> 16.5 | P12: =I12*0.5 -> 5.5 | Q12: =M12+N12+O12+P12 -> 41.25
A13: DANIELE | B13: 45579 | C13: HAVANNA | D13: 1033 | E13: ZF ALIMENTOS (HAVANNA MARILIA) | F13: CALÇA LEGGIN SUPLEX | G13: CALÇA | H13: LEVE | I13: 12 | J13: 65 | K13: 780 | L13: 45593 | M13: =I13*0.25 -> 3 | O13: =I13*3 -> 36 | P13: =I13*0.5 -> 6 | Q13: =M13+N13+O13+P13 -> 45
A14: DANIELE | B14: 45566 | C14: COSMÉTICO | D14: 190 | E14: FILO COSMETICOS | F14: AVENTAL OXFORD MODELO PADRÃO | G14: AVENTAL | H14: LEVE | I14: 100 | J14: 17 | K14: 1700 | L14: 45594 | M14: =I14*0.25 -> 25 | N14: =I14*0.7 -> 70 | O14: =I14*1.5 -> 150 | P14: =I14*0.5 -> 50 | Q14: =M14+N14+O14+P14 -> 295
A15: LETICIA | B15: 45579 | C15: INDUSTRIA | D15: 1041 | E15: NESTING | F15: ETIQUETA ALGODÃO CRU | G15: ETIQUETA | H15: LEVE | I15: 500 | J15: 2.5 | K15: 1250 | L15: 45607 | M15: =I15*0.25 -> 125 | N15: =I15*0.3 -> 150 | O15: =I15*0.15 -> 75 | P15: =I15*0.5 -> 250 | Q15: =M15+N15+O15+P15 -> 600
A16: LETICIA | B16: 45569 | C16: COSMÉTICO | D16: 613 | E16: FLORACTIVE | F16: CAMISETA GOLA CARECA MALHA PV | G16: CAMISETA | H16: LEVE | I16: 100 | J16: 16.5 | K16: 1650 | L16: 45595 | M16: =I16*0.25 -> 25 | N16: =I16*1.5 -> 150 | O16: =I16*1.5 -> 150 | P16: =I16*0.5 -> 50 | Q16: =M16+N16+O16+P16 -> 375
A17: LETICIA | B17: 45573 | C17: COSMÉTICO | D17: 617 | E17: M.D BOSO PROHALL | F17: AVENTAL OXFORD MODELO PADRÃO | G17: AVENTAL | H17: LEVE | I17: 700 | J17: 14 | K17: 9800 | L17: 45595 | M17: =I17*0.25 -> 175 | N17: =I17*0.7 -> 490 | O17: =I17*1.5 -> 1050 | P17: =I17*0.5 -> 350 | Q17: =M17+N17+O17+P17 -> 2065
A18: LETICIA | B18: 45582 | C18: COSMÉTICO | D18: 623 | E18: HRT COSMETICOS (MERLOT) | F18: AVENTAL OXFORD MODELO PADRÃO | G18: AVENTAL | H18: LEVE | I18: 100 | J18: 17.5 | K18: 1750 | L18: 45610 | M18: =I18*0.25 -> 25 | N18: =I18*0.7 -> 70 | O18: =I18*1.5 -> 150 | P18: =I18*0.5 -> 50 | Q18: =M18+N18+O18+P18 -> 295
A19: DANIELE | B19: 45579 | C19: HAVANNA | D19: 1033 | E19: ZF ALIMENTOS (HAVANNA MARILIA) | F19: FAIXA PARA CABELO TORCIDA | G19: FAIXA | H19: LEVE | I19: 10 | J19: 21 | K19: 210 | L19: 45593 | M19: =I19*0.25 -> 2.5 | N19: =I19*0.5 -> 5 | O19: =I19*0.75 -> 7.5 | P19: =I19*0.5 -> 5 | Q19: =M19+N19+O19+P19 -> 20
A20: LETICIA | B20: 45574 | C20: COSMÉTICO | D20: 620 | E20: EAE COSMETICOS | F20: CAMISETA GOLA CARECA MALHA PV | G20: CAMISETA | H20: LEVE | I20: 160 | J20: 35 | K20: 5600 | L20: 45602 | M20: =I20*0.25 -> 40 | N20: =I20*1.5 -> 240 | O20: =I20*1.5 -> 240 | P20: =I20*0.5 -> 80 | Q20: =M20+N20+O20+P20 -> 600
A21: LETICIA | B21: 45574 | C21: INDUSTRIA | D21: 192 | E21: GIRARDI CONFECCAO | F21: CAMISETA GOLA CARECA MALHA PV | G21: CAMISETA | H21: LEVE | I21: 80 | J21: 26.5 | K21: 2120 | L21: 45602 | M21: =I21*0.25 -> 20 | N21: =I21*1.5 -> 120 | O21: =I21*1.5 -> 120 | P21: =I21*0.5 -> 40 | Q21: =M21+N21+O21+P21 -> 300
A22: LETICIA | B22: 45574 | C22: INDUSTRIA | D22: 193 | E22: GIRARDI CONFECCAO | F22: CAMISETA GOLA CARECA MALHA PV | G22: CAMISETA | H22: LEVE | I22: 80 | J22: 26.5 | K22: 2120 | L22: 45603 | M22: =I22*0.25 -> 20 | N22: =I22*1.5 -> 120 | O22: =I22*1.5 -> 120 | P22: =I22*0.5 -> 40 | Q22: =M22+N22+O22+P22 -> 300
A23: DANIELE | B23: 45579 | C23: HAVANNA | D23: 1033 | E23: ZF ALIMENTOS (HAVANNA MARILIA) | F23: AVENTAL OXFORD MODELO PADRÃO | G23: AVENTAL | H23: LEVE | I23: 10 | J23: 21 | K23: 210 | L23: 45593 | M23: =I23*0.25 -> 2.5 | N23: =I23*0.7 -> 7 | O23: =I23*1.5 -> 15 | P23: =I23*0.5 -> 5 | Q23: =M23+N23+O23+P23 -> 29.5
A24: LETICIA | B24: 45579 | C24: BARBEARIA | D24: 197 | E24: DONA NAVALHA BARBEARIA | F24: CAPA DE CORTE TACTEL | G24: CAPA | H24: LEVE | I24: 20 | J24: 80 | K24: 1600 | L24: 45604 | M24: =I24*0.25 -> 5 | N24: =I24*1.5 -> 30 | O24: =I24*2 -> 40 | P24: =I24*0.5 -> 10 | Q24: =M24+N24+O24+P24 -> 85
A25: LETICIA | B25: 45555 | C25: HAVANNA | D25: 1015 | E25: DOCES E DOCES (HAVANNA PRAIA DE BELLAS) | F25: FAIXA PARA CABELO TORCIDA | G25: FAIXA | H25: LEVE | I25: 10 | J25: 21 | K25: 210 | L25: 45593 | M25: =I25*0.25 -> 2.5 | N25: =I25*0.5 -> 5 | O25: =I25*0.75 -> 7.5 | P25: =I25*0.5 -> 5 | Q25: =M25+N25+O25+P25 -> 20
A26: LETICIA | B26: 45580 | C26: INDUSTRIA | D26: 1034 | E26: PLATOLANDIA | F26: CAMISETA GOLA CARECA 100% ALGODÃO | G26: CAMISETA | H26: LEVE | I26: 200 | J26: 26.19 | K26: 5238 | L26: 45608 | M26: =I26*0.25 -> 50 | N26: =I26*1.5 -> 300 | O26: =I26*1.5 -> 300 | P26: =I26*0.5 -> 100 | Q26: =M26+N26+O26+P26 -> 750
A27: LETICIA | B27: 45555 | C27: HAVANNA | D27: 1015 | E27: DOCES E DOCES (HAVANNA PRAIA DE BELLAS) | F27: AVENTAL OXFORD MODELO PADRÃO | G27: AVENTAL | H27: LEVE | I27: 10 | J27: 21 | K27: 210 | L27: 45593 | M27: =I27*0.25 -> 2.5 | N27: =I27*0.7 -> 7 | O27: =I27*1.5 -> 15 | P27: =I27*0.5 -> 5 | Q27: =M27+N27+O27+P27 -> 29.5
A28: DANIELE | B28: 45569 | C28: HAVANNA | D28: 1028 | E28: DRL CAFETERIA (HAVANNA INDAIATUBA) | F28: AVENTAL OXFORD MODELO PADRÃO | G28: AVENTAL | H28: LEVE | I28: 7 | J28: 21 | K28: 147 | L28: 45593 | M28: =I28*0.25 -> 1.75 | N28: =I28*0.7 -> 4.9 | O28: =I28*1.5 -> 10.5 | P28: =I28*0.5 -> 3.5 | Q28: =M28+N28+O28+P28 -> 20.65
A29: LETICIA | B29: 45582 | C29: COSMÉTICO | D29: 623 | E29: HRT COSMETICOS (MERLOT) | F29: CAPA DE CORTE CETIM 0,85 X 1,40 | G29: CAPA | H29: LEVE | I29: 100 | J29: 18.5 | K29: 1850 | L29: 45610 | M29: =I29*0.25 -> 25 | N29: =I29*1.5 -> 150 | O29: =I29*2 -> 200 | P29: =I29*0.5 -> 50 | Q29: =M29+N29+O29+P29 -> 425
A30: LETICIA | B30: 45555 | C30: HAVANNA | D30: 1015 | E30: DOCES E DOCES (HAVANNA PRAIA DE BELLAS) | F30: CAMISETA GOLA CARECA MALHA 100% ALGODÃO | G30: CAMISETA | H30: LEVE | I30: 45 | J30: 36.75 | K30: 1653.75 | L30: 45593 | M30: =I30*0.25 -> 11.25 | N30: =I30*1.5 -> 67.5 | O30: =I30*1.5 -> 67.5 | P30: =I30*0.5 -> 22.5 | Q30: =M30+N30+O30+P30 -> 168.75
A31: LETICIA | B31: 45555 | C31: HAVANNA | D31: 1015 | E31: DOCES E DOCES (HAVANNA PRAIA DE BELLAS) | F31: CAMISETA FEMININA MALHA 100% ALGODÃO MANGA LONGA | G31: CAMISETA | H31: LEVE | I31: 45 | J31: 45 | K31: 2025 | L31: 45593 | M31: =I31*0.25 -> 11.25 | N31: =I31*1.5 -> 67.5 | O31: =I31*1.5 -> 67.5 | P31: =I31*0.5 -> 22.5 | Q31: =M31+N31+O31+P31 -> 168.75
A32: DANIELE | B32: 45569 | C32: HAVANNA | D32: 1028 | E32: DRL CAFETERIA (HAVANNA INDAIATUBA) | F32: FAIXA PARA CABELO TORCIDA | G32: FAIXA | H32: LEVE | I32: 6 | J32: 21 | K32: 126 | L32: 45593 | M32: =I32*0.25 -> 1.5 | N32: =I32*0.5 -> 3 | O32: =I32*0.75 -> 4.5 | P32: =I32*0.5 -> 3 | Q32: =M32+N32+O32+P32 -> 12
A33: DANIELE | B33: 45579 | C33: HAVANNA | D33: 1033 | E33: ZF ALIMENTOS (HAVANNA MARILIA) | F33: CAMISETA FEMININA MALHA 100% ALGODÃO MANGA LONGA | G33: CAMISETA | H33: LEVE | I33: 8 | J33: 47.5 | K33: 380 | L33: 45593 | M33: =I33*0.25 -> 2 | N33: =I33*1.5 -> 12 | O33: =I33*1.5 -> 12 | P33: =I33*0.5 -> 4 | Q33: =M33+N33+O33+P33 -> 30
A34: DANIELE | B34: 45579 | C34: HAVANNA | D34: 1033 | E34: ZF ALIMENTOS (HAVANNA MARILIA) | F34: CAMISETA GOLA CARECA MALHA 100% ALGODÃO | G34: CAMISETA | H34: LEVE | I34: 3 | J34: 36.75 | K34: 110.25 | L34: 45593 | M34: =I34*0.25 -> 0.75 | N34: =I34*1.5 -> 4.5 | O34: =I34*1.5 -> 4.5 | P34: =I34*0.5 -> 1.5 | Q34: =M34+N34+O34+P34 -> 11.25
A35: DANIELE | B35: 45589 | C35: HAVANNA | D35: 1022 | E35: JL COMERCIO DE ALIMENTOS (HAVANNA) | F35: FAIXA PARA CABELO TORCIDA | G35: FAIXA | H35: LEVE | I35: 12 | J35: 21 | K35: 252 | L35: 45593 | M35: =I35*0.25 -> 3 | N35: =I35*0.5 -> 6 | O35: =I35*0.75 -> 9 | P35: =I35*0.5 -> 6 | Q35: =M35+N35+O35+P35 -> 24
A36: LETICIA | B36: 45573 | C36: COSMÉTICO | D36: 617 | E36: M.D BOSO PROHALL | F36: KIMONO CETIM - TAM ÚNICO | G36: KIMONO | H36: LEVE | I36: 400 | J36: 24.5 | K36: 9800 | L36: 45595 | M36: =I36*0.25 -> 100 | N36: =I36*1.5 -> 600 | O36: =I36*10 -> 4000 | P36: =I36*0.5 -> 200 | Q36: =M36+N36+O36+P36 -> 4900
A37: DANIELE | B37: 45589 | C37: HAVANNA | D37: 1022 | E37: JL COMERCIO DE ALIMENTOS (HAVANNA) | F37: AVENTAL OXFORD MODELO PADRÃO | G37: AVENTAL | H37: LEVE | I37: 13 | J37: 21 | K37: 273 | L37: 45593 | M37: =I37*0.25 -> 3.25 | N37: =I37*0.7 -> 9.1 | O37: =I37*1.5 -> 19.5 | P37: =I37*0.5 -> 6.5 | Q37: =M37+N37+O37+P37 -> 38.35
A38: LETICIA | B38: 45555 | C38: HAVANNA | D38: 1015 | E38: DOCES E DOCES (HAVANNA PRAIA DE BELLAS) | F38: CAMISETA MALHA 100% ALGODÃO MANGA LONGA | G38: CAMISETA | H38: LEVE | I38: 25 | J38: 45 | K38: 1125 | L38: 45593 | M38: =I38*0.25 -> 6.25 | N38: =I38*1.5 -> 37.5 | O38: =I38*1.5 -> 37.5 | P38: =I38*0.5 -> 12.5 | Q38: =M38+N38+O38+P38 -> 93.75
A39: DANIELE | B39: 45566 | C39: COSMÉTICO | D39: 190 | E39: FILO COSMETICOS | F39: NECESSAIRE CRISTAL COM VIES | G39: NECESSAIRE | H39: PESADA | I39: 100 | J39: 12 | K39: 1200 | L39: 45594 | M39: =I39*0.25 -> 25 | N39: =I39*0.5 -> 50 | O39: =I39*1.8 -> 180 | P39: =I39*0.5 -> 50 | Q39: =M39+N39+O39+P39 -> 305
A40: DANIELE | B40: 45540 | C40: PET | D40: 194 | E40: MANU PET STORE | F40: AVENTAL PET NY IMPERMEAVEL COM VIES | G40: AVENTAL | H40: LEVE | I40: 100 | J40: 27 | K40: 2700 | L40: 45603 | M40: =I40*0.25 -> 25 | N40: =I40*0.7 -> 70 | O40: =I40*1.5 -> 150 | P40: =I40*0.5 -> 50 | Q40: =M40+N40+O40+P40 -> 295
A41: LETICIA | B41: 45582 | C41: PET | D41: 622 | E41: LDM PELONCIO PET | F41: AVENTAL PET NY IMPERMEAVEL COM VIES | G41: AVENTAL | H41: LEVE | I41: 250 | J41: 21.5 | K41: 5375 | L41: 45609 | M41: =I41*0.25 -> 62.5 | N41: =I41*1 -> 250 | O41: =I37*1.84 -> 23.92 | P41: =I41*0.5 -> 125 | Q41: =M41+N41+O41+P41 -> 461.42
A42: DANIELE | B42: 45569 | C42: HAVANNA | D42: 1028 | E42: DRL CAFETERIA (HAVANNA INDAIATUBA) | F42: CAMISETA GOLA CARECA MALHA 100% ALGODÃO | G42: CAMISETA | H42: LEVE | I42: 6 | J42: 41.75 | K42: 250.5 | L42: 45593 | M42: =I42*0.25 -> 1.5 | N42: =I42*1.5 -> 9 | O42: =I42*1.5 -> 9 | P42: =I42*0.5 -> 3 | Q42: =M42+N42+O42+P42 -> 22.5
A43: DANIELE | B43: 45569 | C43: HAVANNA | D43: 1028 | E43: DRL CAFETERIA (HAVANNA INDAIATUBA) | F43: CAMISETA GOLA CARECA MALHA 100% ALGODÃO | G43: CAMISETA | H43: LEVE | I43: 4 | J43: 36.75 | K43: 147 | L43: 45593 | M43: =I43*0.25 -> 1 | N43: =I43*1.5 -> 6 | O43: =I43*1.5 -> 6 | P43: =I43*0.5 -> 2 | Q43: =M43+N43+O43+P43 -> 15
A44: LETICIA | B44: 45586 | C44: INDUSTRIA | D44: 624 | E44: VOICER STORE COMERCIO E SERVIÇOS | F44: NECESSAIRE NY PLASTIFICADO GRANDE 26L X 20A X 9 | G44: NECESSAIRE | H44: PESADA | I44: 200 | J44: 23 | K44: 4600 | L44: 45614 | M44: =I44*0.25 -> 50 | N44: =I44*0.6 -> 120 | O44: =I44*5 -> 1000 | P44: =I44*0.5 -> 100 | Q44: =M44+N44+O44+P44 -> 1270
A45: LETICIA | B45: 45586 | C45: INDUSTRIA | D45: 624 | E45: VOICER STORE COMERCIO E SERVIÇOS | F45: NECESSAIRE NY PLASTIFICADO PEQUENA 22L X 17A X 5 | G45: NECESSAIRE | H45: PESADA | I45: 500 | J45: 23 | K45: 11500 | L45: 45614 | M45: =I45*0.25 -> 125 | N45: =I45*0.6 -> 300 | O45: =I45*5 -> 2500 | P45: =I45*0.5 -> 250 | Q45: =M45+N45+O45+P45 -> 3175
A46: DANIELE | B46: 45589 | C46: HAVANNA | D46: 1022 | E46: JL COMERCIO DE ALIMENTOS (HAVANNA) | F46: CAMISETA FEMININA MALHA 100% ALGODÃO MANGA LONGA | G46: CAMISETA | H46: LEVE | I46: 10 | J46: 47.5 | K46: 475 | L46: 45593 | M46: =I46*0.25 -> 2.5 | N46: =I46*1.5 -> 15 | O46: =I46*1.5 -> 15 | P46: =I46*0.5 -> 5 | Q46: =M46+N46+O46+P46 -> 37.5
A47: DANIELE | B47: 45589 | C47: HAVANNA | D47: 1022 | E47: JL COMERCIO DE ALIMENTOS (HAVANNA) | F47: CAMISETA GOLA CARECA 100% ALGODÃO | G47: CAMISETA | H47: LEVE | I47: 6 | J47: 36.75 | K47: 220.5 | L47: 45593 | M47: =I47*0.25 -> 1.5 | N47: =I47*1.5 -> 9 | O47: =I47*1.5 -> 9 | P47: =I47*0.5 -> 3 | Q47: =M47+N47+O47+P47 -> 22.5
A48: LETICIA | B48: 45574 | C48: COSMÉTICO | D48: 621 | E48: KOOSMETICS (EXO) | F48: NECESSSAIRE CRISTAL 30A X 16L X 10 - EXO | G48: NECESSAIRE | H48: PESADA | I48: 500 | J48: 7.8 | K48: 3900 | L48: 45595 | M48: =I48*0.25 -> 125 | N48: =I48*0.5 -> 250 | O48: =I48*1.5 -> 750 | P48: =I48*0.5 -> 250 | Q48: =M48+N48+O48+P48 -> 1375
A49: LETICIA | B49: 45565 | C49: PET | D49: 189 | E49: VET RIO | F49: AVENTAL SEMI IMPERMEAVEL | G49: AVENTAL | H49: LEVE | I49: 100 | J49: 19.7 | K49: 1970 | L49: 45593 | M49: =I49*0.25 -> 25 | N49: =I49*0.7 -> 70 | O49: =I49*1.84 -> 184 | P49: =I49*0.5 -> 50 | Q49: =M49+N49+O49+P49 -> 329
A50: LETICIA | B50: 45576 | C50: COSMÉTICO | D50: 195 | E50: GABONI | F50: AVENTAL SEMI IMPERMEAVEL | G50: AVENTAL | H50: LEVE | I50: 100 | J50: 19.5 | K50: 1950 | L50: 45604 | M50: =I50*0.25 -> 25 | N50: =I50*0.7 -> 70 | O50: =I50*1.84 -> 184 | P50: =I50*0.5 -> 50 | Q50: =M50+N50+O50+P50 -> 329
A51: LETICIA | B51: 45565 | C51: EDITORA | D51: 1023 | E51: EDITORA RECORD | F51: SACOLA ALGODÃO CRU 35L X 40A | G51: SACOLA | H51: LEVE | I51: 400 | J51: 10.5 | K51: 4200 | L51: 45593 | M51: =I51*0.25 -> 100 | N51: =I51*1.5 -> 600 | O51: =I51*0.6 -> 240 | P51: =I51*0.5 -> 200 | Q51: =M51+N51+O51+P51 -> 1140
A52: LETICIA | B52: 45573 | C52: EDITORA | D52: 191 | E52: EDITORA GALERA | F52: SAQUINHO ALGODÃO | G52: SACO | H52: LEVE | I52: 4000 | J52: 5.3 | K52: 21200 | L52: 45601 | M52: =I52*0.25 -> 1000 | N52: =I52*0.5 -> 2000 | O52: =I52*0.6 -> 2400 | P52: =I52*0.5 -> 2000 | Q52: =M52+N52+O52+P52 -> 7400
M54: =SUM(M2:M52) -> 3267.5 | N54: =SUM(N3:N52) -> 10827 | O54: =SUM(O3:O52) -> 24176.42 | P54: =SUM(P2:P52) -> 6535 | Q54: =SUM(Q2:Q52) -> 44875.92

Sheet TOTAIS (PLANILHA INATIVA)
B2: CARTEIRA EM PRODUÇÃO | F2: TOTAIS EM CARTEIRA POR GRUPO | L2: CUSTO MÃO DE OBRA
B3: PEÇAS | C3: FATURAR | D3: LIQUIDAR | F3: GRUPO | G3: QTD | H3: FATURAR | I3: LIQUIDAR | L3: EM PRODUÇÃO
B4: ='PCP + MO '!J1629 -> 24489 | C4: ='PCP + MO '!L1629 -> 419654.5 | D4: ='PCP + MO '!M1629 -> 246959.5 | F4: Avental | G4: 5160 | H4: 114359 | I4: 93172.5 | L4: CORTE | M4: ='PCP + MO '!R1629 -> 0
F5: Camiseta | G5: 1863 | H5: 47509.5 | I5: 29076.62 | L5: SILK | M5: ='PCP + MO '!S1629 -> 0
F6: Necessaire | G6: 2000 | H6: 18620 | I6: 10810 | L6: COSTURA | M6: ='PCP + MO '!T1629 -> 0
F7: Capa Protetor | G7: 1500 | H7: 24000 | I7: 24000 | L7: EMBALAGEM | M7: ='PCP + MO '!U1629 -> 0
F8: Kimono | G8: 1190 | H8: 30075 | I8: 27400 | L8: TOTAL | M8: =SUM(M4:M7) -> 0
F9: Capa de Corte | G9: 865 | H9: 19575 | I9: 16262.5
F10: Saco | G10: 400 | H10: 9800 | I10: 9800
F11: Polo | G11: 170 | H11: 8280 | I11: 270
F12: Sacola | G12: 100 | H12: 3500 | I12: 0
F13: Touca | G13: 100 | H13: 1100 | I13: 1100
F14: Etiqueta | G14: 500 | H14: 1250 | I14: 1250
F15: Calça Brim | G15: 25 | H15: 1875 | I15: 1875
F16: Faixa | G16: 44 | H16: 1044 | I16: 960
F17: Moleton | G17: 7 | H17: 595 | I17: 0
F18: Calça Leggin | G18: 1 | H18: 65 | I18: 32.5
F19: TOTAL | G19: =SUM(G4:G18) -> 13925 | H19: =SUM(H4:H18) -> 281647.5 | I19: =SUM(I4:I18) -> 216009.12
F20: Ticket Médio | I20: =H19/G19 -> 20.226032
F21: Margem de Recebimento Antecipado | I21: =100%-I19/H19 -> 0.23305153

Sheet VENDAS (PLANILHA INATIVA)
B2: CARTEIRA EM PRODUÇÃO
B3: Peças
B4: Valores
B6: VENDAS
B7: MÊS | C7: PEDIDOS | D7: ITENS | E7: VALORES
B8: ABRIL | C8: 42 | D8: 19516 | E8: 397092.25
B9: MAIO | C9: 40 | D9: 31359 | E9: 575422.5
B10: JUNHO | C10: 51 | D10: 12014 | E10: 283366.5
B11: JULHO | C11: 42 | D11: 10970 | E11: 221481.5
B12: AGOSTO | C12: =C26 -> 49 | D12: =D26 -> 17849 | E12: =E26 -> 244599.75
B13: SETEMBRO | C13: =C27 -> 43 | D13: =D27 -> 13011 | E13: =E27 -> 279023.5
B14: OUTUBRO | C14: 62 | D14: 18150 | E14: 370963
B15: NOVEMBRO | C15: 48 | D15: 15392 | E15: 255680.25
B16: DEZEMBRO | C16: 19 | D16: 7394 | E16: 151501.5
B17: TOTAL | C17: =SUM(C8:C16) -> 396 | D17: =SUM(D8:D16) -> 145655 | E17: =SUM(E8:E16) -> 2779130.8
B19: TOTAL REALIZADO | F19: MÉDIA REALIZADA | K19: Mês | L19: Vendido | M19: Faturado | N19: Pago
B20: Mês | C20: Pedidos | D20: Peças Vendidas | E20: Valores de Vendas | F20: Dias Uteis | G20: Média de Pedidos Dia | H20: Média de Peças Dia | I20: Média de Valores Dia | K20: ABRIL | L20: 397092.25 | M20: 255543 | N20: 480901.63
K21: MAIO | L21: 575422.5 | M21: 369011 | N21: 503604.63
B22: ABRIL | C22: 42 | D22: 19516 | E22: 397092.25 | F22: 20 | G22: =C22/F22 -> 2.1 | H22: =D22/F22 -> 975.8 | I22: =E22/F22 -> 19854.612 | K22: JUNHO | L22: 283366.5 | M22: 342831.95 | N22: 296535.04
B23: MAIO | C23: 40 | D23: 31359 | E23: 575422.5 | F23: 21 | G23: =C23/F23 -> 1.9047619 | H23: =D23/F23 -> 1493.2857 | I23: =E23/F23 -> 27401.071 | K23: JULHO | L23: 221481.5 | M23: 576329.75 | N23: 401333.98
B24: JUNHO | C24: 51 | D24: 12014 | E24: 283366.5 | F24: 20 | G24: =C24/F24 -> 2.55 | H24: =D24/F24 -> 600.7 | I24: =E24/F24 -> 14168.325 | K24: AGOSTO | L24: =E26 -> 244599.75 | M24: 330213.95 | N24: 297759.34
B25: JULHO | C25: 42 | D25: 10970 | E25: 221481.5 | F25: 22 | G25: =C25/F25 -> 1.9090909 | H25: =D25/F25 -> 498.63636 | I25: =E25/F25 -> 10067.341 | K25: SETEMBRO | L25: =E27 -> 279023.5 | M25: 216774 | N25: 183954.49
B26: AGOSTO | C26: 49 | D26: 17849 | E26: 244599.75 | F26: 21 | G26: =C26/F26 -> 2.3333333 | H26: =D26/F26 -> 849.95238 | I26: =E26/F26 -> 11647.607 | K26: OUTUBRO | L26: =E28 -> 370963
B27: SETEMBRO | C27: 43 | D27: 13011 | E27: 279023.5 | F27: 21 | G27: =C27/F27 -> 2.047619 | H27: =D27/F27 -> 619.57143 | I27: =E27/F27 -> 13286.833
B28: OUTUBRO | C28: 62 | D28: 18150 | E28: 370963 | F28: 23 | G28: =C28/F28 -> 2.6956522 | H28: =D28/F28 -> 789.13043 | I28: =E28/F28 -> 16128.826
B29: NOVEMBRO | C29: 48 | D29: 15392 | E29: 255680.25 | F29: 20 | G29: =C29/F29 -> 2.4 | H29: =D29/F29 -> 769.6 | I29: =E29/F29 -> 12784.013
B31: TOTAL | C31: =SUM(C22:C29) -> 377 | D31: =SUM(D22:D29) -> 138261 | E31: =SUM(E22:E29) -> 2627629.2 | F31: =AVERAGE(F22:F28) -> 21.142857 | G31: =AVERAGE(G22:G27) -> 2.1408009 | H31: =AVERAGE(H22:H27) -> 839.65765 | I31: =AVERAGE(I22:I27) -> 16070.965
B32: MÉDIA | C32: =AVERAGE(C22:C26) -> 44.8 | D32: =AVERAGE(D22:D26) -> 18341.6 | E32: =AVERAGE(E22:E26) -> 344392.5
B34: Realizado proporcional aos meses anteriores
B35: ABRIL | C35: =E29/E22 -> 0.64388124
B36: MAIO | C36: =E29/E23 -> 0.44433481 | G36: Vendido
B37: JUNHO | C37: =E29/E24 -> 0.90229526 | G37: Faturado
B38: JULHO | C38: =E29/E25 -> 1.1544091 | G38: Pago
B39: AGOSTO | C39: =E29/E26 -> 1.0453005
B40: SETEMBRO | C40: =E29/E27 -> 0.91633948
B41: OUTUBRO
B42: NOVEMBRO
B44: MÊS | C44: Vendido | D44: Faturado
B45: ABRIL | C45: 397092.25 | D45: 255543
B46: MAIO | C46: 575422.5 | D46: 369011
B47: JUNHO | C47: 283366.5 | D47: 342831.95
B48: JULHO | C48: 221481.5 | D48: 576329.75
B49: AGOSTO | C49: 244599.75 | D49: 330213.95
B50: SETEMBRO | C50: =E27 -> 279023.5 | D50: 216774
B51: OUTUBRO | C51: =E28 -> 370963
B68: Realizado Por Vendedor - Setembro
B69: Vendedor | C69: Pedidos | D69: Peças | E69: Valor
B70: Amanda | C70: 3 | D70: 307 | E70: 4655
B71: Aracheles | C71: 6 | D71: 835 | E71: 25185
B72: Fernanda | C72: 5 | D72: 124 | E72: 4076.5
B73: Leticia | C73: 29 | D73: 11745 | E73: 245107
B74: Total | C74: =SUM(C70:C73) -> 43 | D74: =SUM(D70:D73) -> 13011 | E74: =SUM(E70:E73) -> 279023.5

Sheet RELATÓRIO HAVANNA
A1: RELATÓRIO DE PEDIDOS HAVANNA
A3: PEDIDO | B3: DATA DO PEDIDO | C3: CLIENTE | D3: PRODUTO | E3: GRUPO | F3: QTD | G3: VALOR UNID | H3: TOTAL
A4: 1101 | B4: 45297 | C4: PATAGONIA CAFÉ LTDA | D4: CAMISETA MALHA 100% ALGODÃO | E4: CAMISETA | F4: 16 | G4: 36.75 | H4: =G4*F4 -> 588
A5: 911 | B5: 45412 | C5: DGA DOCES | D5: SACOLA DE LONITA MODELO HAVANNA | E5: SACOLA | F5: 250 | G5: 16.5 | H5: =G5*F5 -> 4125
A6: 904 | B6: 45419 | C6: DGA DOCES | D6: CAMISETA MALHA 100% ALGODÃO | E6: CAMISETA | F6: 500 | G6: 26.8 | H6: =G6*F6 -> 13400
A7: 912 | B7: 45421 | C7: DGA DOCES | D7: SACOLA SUBLIMADA TECIDO PET | E7: SACOLA | F7: 250 | G7: 19 | H7: =G7*F7 -> 4750
A8: 929 | B8: 45440 | C8: CAFÉ DEL PLATA | D8: CAMISETA MANGA LONGA MALHA 100% ALGODÃO | E8: CAMISETA | F8: 7 | G8: 47.5 | H8: =G8*F8 -> 332.5
A9: 929 | B9: 45440 | C9: CAFÉ DEL PLATA | D9: CAMISETA MALHA 100% ALGODÃO | E9: CAMISETA | F9: 7 | G9: 33.88 | H9: =G9*F9 -> 237.16
A10: 929 | B10: 45440 | C10: CAFÉ DEL PLATA | D10: CAMISETA MALHA 100% ALGODÃO BABY LOOK | E10: CAMISETA | F10: 4 | G10: 33.88 | H10: =G10*F10 -> 135.52
A11: 929 | B11: 45440 | C11: CAFÉ DEL PLATA | D11: CAMISETA MANGA LONGA MALHA 100% ALGODÃO BABY LOOK | E11: CAMISETA | F11: 4 | G11: 47.5 | H11: =G11*F11 -> 190
A12: 928 | B12: 45440 | C12: CAFÉ DEL PLATA | D12: CAMISETA MANGA LONGA MALHA 100% ALGODÃO | E12: CAMISETA | F12: 7 | G12: 47.5 | H12: =G12*F12 -> 332.5
A13: 928 | B13: 45440 | C13: CAFÉ DEL PLATA | D13: CAMISETA MALHA 100% ALGODÃO | E13: CAMISETA | F13: 7 | G13: 33.88 | H13: =G13*F13 -> 237.16
A14: 928 | B14: 45440 | C14: CAFÉ DEL PLATA | D14: CAMISETA MALHA 100% ALGODÃO BABY LOOK | E14: CAMISETA | F14: 4 | G14: 33.88 | H14: =G14*F14 -> 135.52
A15: 928 | B15: 45440 | C15: CAFÉ DEL PLATA | D15: CAMISETA MANGA LONGA MALHA 100% ALGODÃO BABY LOOK | E15: CAMISETA | F15: 4 | G15: 47.5 | H15: =G15*F15 -> 190
... A570: 637 | B570: 46219 | C570: J.A DA CAMARA FERNANDEZ | D570: POLO PIQUET | E570: POLO | F570: 2 | G570: 65 | H570: =G570*F570 -> 130
F574: =SUM(F4:F573) -> 5510 | H574: =SUM(H4:H573) -> 198103.11
F575: Peças | H575: Faturamento

Sheet VENDAS HAVANNA 2026
B1: 2026
B3: VENDAS HAVANNA | C3: MÊS | D3: PEÇAS | E3: VALORES
C4: JANEIRO | D4: 115 | E4: 3533
C5: FEVEREIRO | D5: 48 | E5: 1693.5
C6: MARÇO | D6: 140 | E6: 5267
C7: ABRIL | D7: 53 | E7: 1715
C8: MAIO | D8: 24 | E8: 1354.5
C9: JUNHO | D9: 241 | E9: 9717.5
C10: JULHO
C11: AGOSTO
C12: SETEMBRO
C13: OUTUBRO
C14: NOVEMBRO
C15: DEZEMBRO
C16: TOTAL | D16: =SUM(D4:D15) -> 621 | E16: =SUM(E4:F15) -> 23280.5
B19: VENDAS HAVANNA - QTD PEÇAS | P19: VENDAS HAVANNA - VALORES
B20: ITEM | C20: JAN | D20: FEV | E20: MAR | F20: ABR | G20: MAI | H20: JUN | I20: JUL | J20: AGO | K20: SET | L20: OUT | M20: NOV | N20: TOTAL | P20: ITEM | Q20: JAN | R20: FEV | S20: MAR | T20: ABR | U20: MAIO | V20: JUNHO | W20: JULHO | X20: AGOSTO | Y20: SETEMBRO | Z20: OUTUBRO | AA20: NOVEMBRO | AB20: TOTAL
B21: AVENTAIS | C21: 37 | D21: 13 | E21: 25 | F21: 12 | G21: 1 | H21: 66 | N21: =SUM(C21:M21) -> 154 | P21: AVENTAIS | Q21: =C21*25 -> 925 | R21: =D21*25 -> 325 | S21: =E21*25 -> 625 | T21: =F21*25 -> 300 | AB21: =SUM(Q21:AA21) -> 2175
B22: CAMISETA GOLA CARECA | C22: 48 | D22: 10 | E22: 49 | F22: 24 | G22: 10 | H22: 101 | N22: =SUM(C22:M22) -> 242 | P22: CAMISETA GOLA CARECA | Q22: =C22*36.75 -> 1764 | R22: 432 | S22: =E22*36.75 -> 1800.75 | T22: =F22*36.75 -> 882 | AB22: =SUM(Q22:AA22) -> 4878.75
B23: CAMISETA MANGA LONGA | C23: 8 | D23: 18 | E23: 27 | F23: 0 | H23: 19 | N23: =SUM(C23:L23) -> 72 | P23: CAMISETA MANGA LONGA | Q23: =C23*36.75 -> 294 | R23: =D23*36.75 -> 661.5 | S23: =E23*36.75 -> 992.25 | T23: =F23*36.75 -> 0 | AB23: =SUM(Q23:Z23) -> 1947.75
B24: POLO | C24: 2 | D24: 0 | E24: 6 | F24: 4 | H24: 6 | N24: =SUM(C24:M24) -> 18 | P24: POLO | Q24: =C24*65 -> 130 | R24: =D24*65 -> 0 | S24: =E24*65 -> 390 | T24: =F24*65 -> 260 | AB24: =SUM(Q24:AA24) -> 780
B25: CALÇA | C25: 0 | D25: 0 | E25: 13 | G25: 5 | H25: 3 | N25: =SUM(C25:L25) -> 21 | P25: CALÇA | Q25: =C25*75 -> 0 | R25: =D25*75 -> 0 | S25: =E25*75 -> 975 | T25: =F25*75 -> 0 | AB25: =SUM(Q25:Z25) -> 975
B26: FAIXA P/ CABELO | C26: 20 | D26: 5 | E26: 19 | F26: 13 | G26: 2 | H26: 28 | N26: =SUM(C26:M26) -> 87 | P26: FAIXA P/ CABELO | Q26: =C26*21 -> 420 | R26: =D26*21 -> 105 | S26: =E26*21 -> 399 | T26: =F26*21 -> 273 | AB26: =SUM(Q26:AA26) -> 1197
B27: MOLETOM | C27: 0 | D27: 2 | E27: 1 | G27: 6 | H27: 18 | N27: =SUM(C27:M27) -> 27 | P27: MOLETOM | Q27: =C27*85 -> 0 | R27: =D27*85 -> 170 | S27: =E27*85 -> 85 | T27: =F27*85 -> 0 | AB27: =SUM(Q27:AA27) -> 255
B28: TOTAL | C28: =SUM(C21:C27) -> 115 | D28: =SUM(D21:D27) -> 48 | E28: =SUM(E21:E27) -> 140 | F28: =SUM(F21:F27) -> 53 | G28: =SUM(G21:G27) -> 24 | H28: =SUM(H21:H27) -> 241 | I28: =SUM(I21:I27) -> 0 | J28: =SUM(J21:J27) -> 0 | ... M28: =SUM(M21:M27) -> 0 | N28: =SUM(C28:M28) -> 621 | P28: TOTAL | Q28: =SUM(Q21:Q27) -> 3533 | R28: =SUM(R21:R27) -> 1693.5 | S28: =SUM(S21:S27) -> 5267 | T28: =SUM(T21:T27) -> 1715 | U28: =SUM(U21:U27) -> 0 | V28: =SUM(V21:V27) -> 0 | W28: =SUM(W21:W27) -> 0 | X28: =SUM(X21:X27) -> 0 | ... AA28: =SUM(AA21:AA27) -> 0 | AB28: =SUM(Q28:Z28) -> 12208.5
B50: 2025
B52: VENDAS HAVANNA | C52: MÊS | D52: PEÇAS | E52: VALORES
C53: JANEIRO
C54: FEVEREIRO
C55: MARÇO
C56: ABRIL | D56: 323 | E56: 14395.5
C57: MAIO | D57: 183 | E57: 6739.5
C58: JUNHO | D58: 140 | E58: 5457
C59: JULHO | D59: 400 | E59: 15117.5
C60: AGOSTO | D60: 165 | E60: 7687.25
C61: SETEMBRO | D61: 27 | E61: 1193.5
C62: OUTUBRO | D62: 307 | E62: 11683
C63: NOVEMBRO | D63: 49 | E63: 1873.25
C64: DEZEMBRO | D64: 41 | E64: 1768.25
C65: TOTAL | D65: =SUM(D53:D64) -> 1635 | E65: =SUM(E53:F64) -> 65914.75
B68: VENDAS HAVANNA - QTD PEÇAS | Q68: VENDAS HAVANNA - VALORES
B69: ITEM | C69: JAN | D69: FEV | E69: MAR | F69: ABR | G69: MAI | H69: JUN | I69: JUL | J69: AGO | K69: SET | L69: OUT | M69: NOV | N69: DEZEMBRO | O69: TOTAL | Q69: ITEM | R69: JAN | S69: FEV | T69: MAR | U69: ABR | V69: MAIO | W69: JUNHO | X69: JULHO | Y69: AGOSTO | Z69: SETEMBRO | AA69: OUTUBRO | AB69: NOVEMBRO | AC69: DEZEMBRO | AD69: TOTAL
B70: AVENTAIS | F70: 42 | G70: 42 | H70: 43 | I70: 67 | J70: 33 | K70: 2 | L70: 58 | M70: 8 | N70: 6 | O70: =SUM(C70:N70) -> 301 | Q70: AVENTAIS | R70: =C70*25 -> 0 | S70: =D70*25 -> 0 | T70: =E70*25 -> 0 | U70: =F70*25 -> 1050 | V70: 1073.5 | W70: =H70*25 -> 1075 | X70: =I70*25 -> 1675 | Y70: =J70*25 -> 825 | Z70: =K70*25 -> 50 | AA70: 1330 | AB70: =M70*25 -> 200 | AC70: =N70*25 -> 150 | AD70: =SUM(R70:AC70) -> 7428.5
B71: CAMISETAS GOLA CARECA | F71: 104 | G71: 61 | H71: 46 | I71: 203 | J71: 46 | K71: 13 | L71: 113 | M71: 25 | N71: 26 | O71: =SUM(C71:N71) -> 637 | Q71: CAMISETAS GOLA CARECA | U71: 4105.5 | V71: 2280.75 | W71: 1768.5 | X71: 8394.75 | Y71: 1830.25 | Z71: 544.75 | AA71: 4367.75 | AB71: 918.75 | AC71: 1141.25 | AD71: =SUM(R71:AC71) -> 25352.25
B72: BABY LOOK | F72: 52 | G72: 42 | H72: 14 | I72: 57 | J72: 24 | K72: 7 | L72: 35 | M72: 6 | N72: 4 | O72: =SUM(C72:N72) -> 241 | Q72: BABY LOOK | U72: 1911 | V72: 1543.25 | W72: 514.5 | X72: =I72*36.75 -> 2094.75 | Y72: 882 | Z72: 273.75 | AA72: =L72*36.75 -> 1286.25 | AB72: 220.5 | AC72: =N72*36.75 -> 147 | AD72: =SUM(R72:AC72) -> 8873
B73: POLO | F73: 23 | G73: 5 | H73: 4 | I73: 14 | J73: 10 | K73: 4 | L73: 15 | M73: 3 | N73: 5 | O73: =SUM(C73:N73) -> 83 | Q73: POLO | U73: 1235 | V73: 325 | W73: 260 | X73: 910 | Y73: =J73*65 -> 650 | Z73: =K73*65 -> 260 | AA73: =L73*65 -> 975 | AB73: =M73*65 -> 195 | AC73: 330 | AD73: =SUM(R73:AC73) -> 5140
B74: CALÇA | F74: 74 | G74: 13 | H74: 1 | I74: 5 | J74: 28 | K74: 1 | L74: 25 | M74: 0 | N74: 0 | O74: =SUM(C74:N74) -> 147 | Q74: CALÇA | U74: 5250 | V74: 905 | W74: 65 | X74: =I74*75 -> 375 | Y74: =J74*75 -> 2100 | Z74: 65 | AA74: =L74*75 -> 1875 | AC74: 0 | AD74: =SUM(U74:AC74) -> 10635
B75: FAIXA P/ CABELO | F75: 24 | G75: 17 | H75: 14 | I75: 46 | J75: 10 | K75: 0 | L75: 54 | M75: 4 | N75: 0 | O75: =SUM(C75:N75) -> 169 | Q75: FAIXA P/ CABELO | U75: 504 | V75: 357 | W75: 279 | X75: 988 | Y75: =J75*21 -> 210 | Z75: 0 | AA75: 1254 | AB75: =M75*21 -> 84 | AC75: 0 | AD75: =SUM(R75:AC75) -> 3676
B76: MOLETOM | F76: 4 | G76: 3 | H76: 18 | I76: 8 | J76: 14 | K76: 0 | L76: 7 | M76: 3 | N76: 0 | O76: =SUM(C76:N76) -> 57 | Q76: MOLETOM | U76: 340 | V76: 255 | W76: 1495 | X76: 680 | Y76: =J76*85 -> 1190 | Z76: 0 | AA76: 595 | AB76: =M76*85 -> 255 | AC76: 0 | AD76: =SUM(R76:AC76) -> 4810
B77: TOTAL | C77: =SUM(C70:C76) -> 0 | D77: =SUM(D70:D76) -> 0 | F77: =SUM(F70:F76) -> 323 | G77: =SUM(G70:G76) -> 183 | H77: =SUM(H70:H76) -> 140 | I77: =SUM(I70:I76) -> 400 | J77: =SUM(J70:J76) -> 165 | K77: =SUM(K70:K76) -> 27 | L77: =SUM(L70:L76) -> 307 | M77: =SUM(M70:M76) -> 49 | N77: =SUM(N70:N76) -> 41 | O77: =SUM(C77:N77) -> 1635 | Q77: TOTAL | R77: =SUM(R70:R76) -> 0 | S77: =SUM(S70:S76) -> 0 | T77: =SUM(T70:T76) -> 0 | U77: =SUM(U70:U76) -> 14395.5 | V77: =SUM(V70:V76) -> 6739.5 | W77: =SUM(W70:W76) -> 5457 | X77: =SUM(X70:X76) -> 15117.5 | Y77: =SUM(Y70:Y76) -> 7687.25 | ... AD77: =SUM(AD70:AD76) -> 65914.75

Sheet PEDIDOS DO MÊS
A2: SEMANA DO PEDIDO | B2: (Tudo)
E4: Valores
A5: Anos (DATA DO PEDIDO) | B5: DATA DO PEDIDO | C5: CLIENTE | D5: PEDIDO | E5: Soma de QTD | F5: Soma de TOTAL
A6: 2026 | B6: 46266 | C6: CAPOBIANGO | D6: 254 | E6: 5 | F6: 216
C7: ROYAL BEAUTY | D7: 253 | E7: 250 | F7: 4125
B8: 46267 | C8: KPRO | D8: 1163 | E8: 500 | F8: 5750
B9: 46268 | C9: BUBBLES PET | D9: 1164 | E9: 300 | F9: 7350
A10: Total Geral | E10: 1055 | F10: 17441

Sheet PCP + MO 
A1: VENDEDOR | B1: PEDIDO | C1: DATA DO PEDIDO | D1: SEMANA DO PEDIDO | E1: CATEGORIA | F1: CLIENTE | G1: PRODUTO | H1: GRUPO | I1: LINHA | J1: QTD | K1: VALOR UNID | L1: TOTAL | M1: LIQUIDAÇÃO | N1: DATA ENTREGA | O1: SEMANA DE ENTREGA | P1: MATERIA PRIMA | Q1: ENTREGA | R1: MO CORTE | S1: MO SILK | T1: MO COSTURA | U1: MO EMBALAGEM | V1: TOTAL
A2: CONSERV | B2: 662 | C2: 45294 | D2: =WEEKNUM(C2) -> 1 | E2: COSMÉTICO | F2: M.D BOSO (PROHALL) | G2: AVENTAL OXFORD MODELO PADRÃO | H2: AVENTAL | I2: LEVE | J2: 200 | K2: 14 | L2: =J2*K2 -> 2800 | M2: 0 | N2: 45311 | O2: =WEEKNUM(N2) -> 3 | P2: OK | Q2: ENTREGUE | R2: =J2*0.25 -> 50 | S2: =J2*0.7 -> 140 | T2: =J2*1.5 -> 300 | U2: =J2*0.5 -> 100 | V2: =R2+S2+T2+U2 -> 590
A3: CONSERV | B3: 1099 | C3: 45297 | D3: =WEEKNUM(C3) -> 1 | E3: PET | F3: CEQ (PET SOCIETY) | G3: AVENTAL NYLON EMBORRACHADO CA 45305 | H3: AVENTAL | I3: LEVE | J3: 2500 | K3: 23.5 | L3: =J3*K3 -> 58750 | M3: 0 | N3: 45339 | O3: =WEEKNUM(N3) -> 7 | Q3: ENTREGUE | R3: =J3*0.25 -> 625 | S3: =J3*1 -> 2500 | T3: =J3*1.65 -> 4125 | U3: =J3*0.5 -> 1250 | V3: =R3+S3+T3+U3 -> 8500
A4: CONSERV | B4: 1101 | C4: 45297 | D4: =WEEKNUM(C4) -> 1 | E4: HAVANNA | F4: PATAGONIA CAFÉ LTDA | G4: CAMISETA MALHA 100% ALGODÃO | H4: CAMISETA | I4: LEVE | J4: 16 | K4: 36.75 | L4: =K4*J4 -> 588 | M4: 0 | N4: 45297 | O4: =WEEKNUM(N4) -> 1 | Q4: ENTREGUE
A5: CONSERV | B5: 911 | C5: 45412 | D5: =WEEKNUM(C5) -> 18 | E5: HAVANNA | F5: DGA DOCES | G5: SACOLA DE LONITA MODELO HAVANNA | H5: SACOLA | I5: PESADA | J5: 250 | K5: 16.5 | L5: =K5*J5 -> 4125 | M5: 0 | N5: 45428 | O5: =WEEKNUM(N5) -> 20 | Q5: ENTREGUE
A6: CONSERV | B6: 904 | C6: 45419 | D6: =WEEKNUM(C6) -> 19 | E6: HAVANNA | F6: DGA DOCES | G6: CAMISETA MALHA 100% ALGODÃO | H6: CAMISETA | I6: LEVE | J6: 500 | K6: 26.8 | L6: =K6*J6 -> 13400 | M6: 0 | N6: 45448 | O6: =WEEKNUM(N6) -> 23 | Q6: ENTREGUE
A7: CONSERV | B7: 912 | C7: 45421 | D7: =WEEKNUM(C7) -> 19 | E7: HAVANNA | F7: DGA DOCES | G7: SACOLA SUBLIMADA TECIDO PET | H7: SACOLA | I7: PESADA | J7: 250 | K7: 19 | L7: =K7*J7 -> 4750 | M7: 0 | N7: 45429 | O7: =WEEKNUM(N7) -> 20 | Q7: ENTREGUE
A8: CONSERV | B8: 929 | C8: 45440 | D8: =WEEKNUM(C8) -> 22 | E8: HAVANNA | F8: CAFÉ DEL PLATA | G8: CAMISETA MANGA LONGA 100% ALGODÃO | H8: CAMISETA | I8: LEVE | J8: 7 | K8: 47.5 | L8: =K8*J8 -> 332.5 | M8: 0 | N8: 45450 | O8: =WEEKNUM(N8) -> 23 | Q8: ENTREGUE
A9: CONSERV | B9: 929 | C9: 45440 | D9: =WEEKNUM(C9) -> 22 | E9: HAVANNA | F9: CAFÉ DEL PLATA | G9: CAMISETA MALHA 100% ALGODÃO | H9: CAMISETA | I9: LEVE | J9: 7 | K9: 33.88 | L9: =K9*J9 -> 237.16 | M9: 0 | N9: 45450 | O9: =WEEKNUM(N9) -> 23 | Q9: ENTREGUE
A10: CONSERV | B10: 929 | C10: 45440 | D10: =WEEKNUM(C10) -> 22 | E10: HAVANNA | F10: CAFÉ DEL PLATA | G10: CAMISETA MALHA 100% ALGODÃO BABY LOOK | H10: CAMISETA | I10: LEVE | J10: 4 | K10: 33.88 | L10: =K10*J10 -> 135.52 | M10: 0 | N10: 45450 | O10: =WEEKNUM(N10) -> 23 | Q10: ENTREGUE
A11: CONSERV | B11: 929 | C11: 45440 | D11: =WEEKNUM(C11) -> 22 | E11: HAVANNA | F11: CAFÉ DEL PLATA | G11: CAMISETA MANGA LONGA 100% ALGODÃO BABY LOOK | H11: CAMISETA | I11: LEVE | J11: 4 | K11: 47.5 | L11: =K11*J11 -> 190 | M11: 0 | N11: 45450 | O11: =WEEKNUM(N11) -> 23 | Q11: ENTREGUE
A12: CONSERV | B12: 928 | C12: 45440 | D12: =WEEKNUM(C12) -> 22 | E12: HAVANNA | F12: CAFÉ DEL PLATA | G12: CAMISETA MANGA LONGA 100% ALGODÃO | H12: CAMISETA | I12: LEVE | J12: 7 | K12: 47.5 | L12: =K12*J12 -> 332.5 | M12: 0 | N12: 45450 | O12: =WEEKNUM(N12) -> 23 | Q12: ENTREGUE
A13: CONSERV | B13: 928 | C13: 45440 | D13: =WEEKNUM(C13) -> 22 | E13: HAVANNA | F13: CAFÉ DEL PLATA | G13: CAMISETA MALHA 100% ALGODÃO | H13: CAMISETA | I13: LEVE | J13: 7 | K13: 33.88 | L13: =K13*J13 -> 237.16 | M13: 0 | N13: 45450 | O13: =WEEKNUM(N13) -> 23 | Q13: ENTREGUE
A14: CONSERV | B14: 928 | C14: 45440 | D14: =WEEKNUM(C14) -> 22 | E14: HAVANNA | F14: CAFÉ DEL PLATA | G14: CAMISETA MALHA 100% ALGODÃO BABY LOOK | H14: CAMISETA | I14: LEVE | J14: 4 | K14: 33.88 | L14: =K14*J14 -> 135.52 | M14: 0 | N14: 45450 | O14: =WEEKNUM(N14) -> 23 | Q14: ENTREGUE
A15: CONSERV | B15: 928 | C15: 45440 | D15: =WEEKNUM(C15) -> 22 | E15: HAVANNA | F15: CAFÉ DEL PLATA | G15: CAMISETA MANGA LONGA 100% ALGODÃO BABY LOOK | H15: CAMISETA | I15: LEVE | J15: 4 | K15: 47.5 | L15: =K15*J15 -> 190 | M15: 0 | N15: 45450 | O15: =WEEKNUM(N15) -> 23 | Q15: ENTREGUE
... A27: CONSERV | B27: 946 | C27: 45485 | D27: =WEEKNUM(C27) -> 28 | E27: HAVANNA | F27: LECEVY COMERCIO DE ALIMENTOS | G27: CAMISETA MANGA LONGA MALHA 100% ALGODÃO | H27: CAMISETA | I27: LEVE | J27: 6 | K27: 48.5 | L27: =K27*J27 -> 291 | M27: 0 | N27: 45527 | O27: =WEEKNUM(N27) -> 34 | Q27: ENTREGUE
A28: CONSERV | B28: 947 | C28: 45490 | D28: =WEEKNUM(C28) -> 29 | E28: HAVANNA | F28: JS ALIMENTAÇÃO | G28: CALÇA LEGGING | H28: CALÇA | I28: LEVE | J28: 10 | K28: 65 | L28: =K28*J28 -> 650 | M28: =L28 -> 650 | N28: 46260 | Q28: ENTREGUE
A29: CONSERV | B29: 947 | C29: 45490 | D29: =WEEKNUM(C29) -> 29 | E29: HAVANNA | F29: JS ALIMENTAÇÃO | G29: CAMISETA MALHA PV GOLA CARECA | H29: CAMISETA | I29: LEVE | J29: 10 | K29: 48.5 | L29: =K29*J29 -> 485 | M29: =L29 -> 485 | N29: 46260 | Q29: ENTREGUE
A30: CONSERV | B30: 947 | C30: 45490 | D30: =WEEKNUM(C30) -> 29 | E30: HAVANNA | F30: JS ALIMENTAÇÃO | G30: AVENTAL OXFORD MODELO PADRÃO | H30: AVENTAL | I30: LEVE | J30: 15 | K30: 62 | L30: =K30*J30 -> 930 | M30: =L30 -> 930 | N30: 46260 | Q30: ENTREGUE
A31: CONSERV | B31: 947 | C31: 45490 | D31: =WEEKNUM(C31) -> 29 | E31: HAVANNA | F31: JS ALIMENTAÇÃO | G31: FAIXA DE CABELO | H31: FAIXA | I31: LEVE | J31: 15 | K31: 21 | L31: =K31*J31 -> 315 | M31: =L31 -> 315 | N31: 46260 | Q31: ENTREGUE
A32: CONSERV | B32: 967 | C32: 45498 | D32: =WEEKNUM(C32) -> 30 | E32: HAVANNA | F32: J.A DA CAMARA FERNANDES | G32: BLUSA DE MOLETOM | H32: AVENTAL | I32: LEVE | J32: 17 | K32: 79.1 | L32: =K32*J32 -> 1344.7 | M32: 0 | N32: 45531 | O32: =WEEKNUM(N32) -> 35 | Q32: ENTREGUE
A33: CONSERV | B33: 967 | C33: 45498 | D33: =WEEKNUM(C33) -> 30 | E33: HAVANNA | F33: J.A DA CAMARA FERNANDES | G33: BLUSA DE MOLETOM | H33: MOLETOM | I33: LEVE | J33: 7 | K33: 62 | L33: =K33*J33 -> 434 | M33: 0 | N33: 45531 | O33: =WEEKNUM(N33) -> 35 | Q33: ENTREGUE
A34: CONSERV | B34: 970 | C34: 45506 | D34: =WEEKNUM(C34) -> 31 | E34: HAVANNA | F34: H4 CAFES E ALIMENTOS | G34: AVENTAL OXFORD MODELO PADRÃO | H34: AVENTAL | I34: LEVE | J34: 10 | K34: 62 | L34: =K34*J34 -> 620 | M34: 0 | N34: 45534 | O34: =WEEKNUM(N34) -> 35 | Q34: ENTREGUE
A35: CONSERV | B35: 970 | C35: 45506 | D35: =WEEKNUM(C35) -> 31 | E35: HAVANNA | F35: H4 CAFES E ALIMENTOS | G35: CAMISETA MALHA PV BABY LOOK | H35: CAMISETA | I35: LEVE | J35: 6 | K35: 48.9 | L35: =K35*J35 -> 293.4 | M35: 0 | N35: 45534 | O35: =WEEKNUM(N35) -> 35 | Q35: ENTREGUE
A36: CONSERV | B36: 970 | C36: 45506 | D36: =WEEKNUM(C36) -> 31 | E36: HAVANNA | F36: H4 CAFES E ALIMENTOS | G36: CALÇA LEGGING | H36: CALÇA | I36: LEVE | J36: 8 | K36: 65 | L36: =K36*J36 -> 520 | M36: 0 | N36: 45534 | O36: =WEEKNUM(N36) -> 35 | Q36: ENTREGUE
A37: CONSERV | B37: 970 | C37: 45506 | D37: =WEEKNUM(C37) -> 31 | E37: HAVANNA | F37: H4 CAFES E ALIMENTOS | G37: FAIXA DE CABELO | H37: FAIXA | I37: LEVE | J37: 6 | K37: 21 | L37: =K37*J37 -> 126 | M37: 0 | N37: 45534 | O37: =WEEKNUM(N37) -> 35 | Q37: ENTREGUE
A38: CONSERV | B38: 970 | C38: 45506 | D38: =WEEKNUM(C38) -> 31 | E38: HAVANNA | F38: H4 CAFES E ALIMENTOS | G38: CAMISETA MALHA PV GOLA CARECA | H38: CAMISETA | I38: LEVE | J38: 9 | K38: 48.5 | L38: =K38*J38 -> 436.5 | M38: 0 | N38: 45534 | O38: =WEEKNUM(N38) -> 35 | Q38: ENTREGUE
A39: CONSERV | B39: 966 | C39: 45509 | D39: =WEEKNUM(C39) -> 32 | E39: HAVANNA | F39: JSC CAFETERIA LTDA | G39: CAMISETA MALHA 100% ALGODÃO BABY LOOK | H39: CAMISETA | I39: LEVE | J39: 2 | K39: 48.5 | L39: =K39*J39 -> 97 | M39: 0 | N39: 45510 | O39: =WEEKNUM(N39) -> 32 | Q39: ENTREGUE
A40: CONSERV | B40: 966 | C40: 45509 | D40: =WEEKNUM(C40) -> 32 | E40: HAVANNA | F40: JSC CAFETERIA LTDA | G40: AVENTAL OXFORD MODELO PADRÃO | H40: AVENTAL | I40: LEVE | J40: 1 | K40: 62 | L40: =K40*J40 -> 62 | M40: 0 | N40: 45510 | O40: =WEEKNUM(N40) -> 32 | Q40: ENTREGUE
A41: CONSERV | B41: 966 | C41: 45509 | D41: =WEEKNUM(C41) -> 32 | E41: HAVANNA | F41: JSC CAFETERIA LTDA | G41: CAMISETA MALHA PV | H41: CAMISETA | I41: LEVE | J41: 2 | K41: 48.5 | L41: =K41*J41 -> 97 | M41: 0 | N41: 45510 | O41: =WEEKNUM(N41) -> 32 | Q41: ENTREGUE
A42: CONSERV | B42: 966 | C42: 45509 | D42: =WEEKNUM(C42) -> 32 | E42: HAVANNA | F42: JSC CAFETERIA LTDA | G42: CALÇA LEGGING | H42: CALÇA | I42: LEVE | J42: 1 | K42: 65 | L42: =K42*J42 -> 65 | M42: 0 | N42: 45510 | O42: =WEEKNUM(N42) -> 32 | Q42: ENTREGUE
A43: CONSERV | B43: 966 | C43: 45509 | D43: =WEEKNUM(C43) -> 32 | E43: HAVANNA | F43: JSC CAFETERIA LTDA | G43: FAIXA DE CABELO | H43: FAIXA | I43: LEVE | J43: 5 | K43: 21 | L43: =K43*J43 -> 105 | M43: 0 | N43: 45510 | O43: =WEEKNUM(N43) -> 32 | Q43: ENTREGUE
... A160: CONSERV | B160: 1065 | C160: 45615 | D160: =WEEKNUM(C160) -> 47 | E160: HAVANNA | F160: MAV COMERCIO DE ALIMENTOS | G160: FAIXA DE CABELO | H160: FAIXA | I160: LEVE | J160: 8 | K160: 21 | L160: =K160*J160 -> 168 | M160: 0 | N160: 45636 | O160: =WEEKNUM(N160) -> 50 | Q160: ENTREGUE
A161: CONSERV | B161: 1068 | C161: 45617 | D161: =WEEKNUM(C161) -> 47 | E161: HAVANNA | F161: HAVANNA RT | G161: CALÇA LEGGING | H161: CALÇA | I161: LEVE | J161: 9 | K161: 75 | L161: =J161*K161 -> 675 | M161: 0 | N161: 45663 | O161: =WEEKNUM(N161) -> 2 | P161: OK | Q161: ENTREGUE | R161: =J161*0.25 -> 2.25 | T161: =J161*3 -> 27 | U161: =J161*0.5 -> 4.5 | V161: =R161+S161+T161+U161 -> 33.75
A162: CONSERV | B162: 1067 | C162: 45617 | D162: =WEEKNUM(C162) -> 47 | E162: HAVANNA | F162: J.A DA CAMARA FERNANDES | G162: CAMISETA MALHA 100% ALGODÃO | H162: CAMISETA | I162: LEVE | J162: 8 | K162: 36.75 | L162: =K162*J162 -> 294 | M162: 0 | N162: 45660 | O162: =WEEKNUM(N162) -> 1 | Q162: ENTREGUE
A163: CONSERV | B163: 1067 | C163: 45617 | D163: =WEEKNUM(C163) -> 47 | E163: HAVANNA | F163: J.A DA CAMARA FERNANDES | G163: CALÇA BRIM | H163: CALÇA | I163: PESADA | J163: 8 | K163: 75 | L163: =K163*J163 -> 600 | M163: 0 | N163: 45660 | O163: =WEEKNUM(N163) -> 1 | Q163: ENTREGUE
A164: CONSERV | B164: 1067 | C164: 45617 | D164: =WEEKNUM(C164) -> 47 | E164: HAVANNA | F164: J.A DA CAMARA FERNANDES | G164: CAMISETA MALHA 100% ALGODÃO BABY LOOK | H164: CAMISETA | I164: LEVE | J164: 12 | K164: 36.75 | L164: =K164*J164 -> 441 | M164: 0 | N164: 45660 | O164: =WEEKNUM(N164) -> 1 | Q164: ENTREGUE
A165: CONSERV | B165: 1067 | C165: 45617 | D165: =WEEKNUM(C165) -> 47 | E165: HAVANNA | F165: J.A DA CAMARA FERNANDES | G165: CALÇA LEGGING | H165: CALÇA | I165: LEVE | J165: 12 | K165: 65 | L165: =K165*J165 -> 780 | M165: 0 | N165: 45660 | O165: =WEEKNUM(N165) -> 1 | Q165: ENTREGUE
A166: CONSERV | B166: 1067 | C166: 45617 | D166: =WEEKNUM(C166) -> 47 | E166: HAVANNA | F166: J.A DA CAMARA FERNANDES | G166: FAIXA DE CABELO | H166: FAIXA | I166: LEVE | J166: 8 | K166: 21 | L166: =K166*J166 -> 168 | M166: 0 | N166: 45660 | O166: =WEEKNUM(N166) -> 1 | Q166: ENTREGUE
A167: CONSERV | B167: 1067 | C167: 45617 | D167: =WEEKNUM(C167) -> 47 | E167: HAVANNA | F167: J.A DA CAMARA FERNANDES | G167: AVENTAL OXFORD MODELO PADRÃO | H167: AVENTAL | I167: LEVE | J167: 12 | K167: 25 | L167: =K167*J167 -> 300 | M167: 0 | N167: 45660 | O167: =WEEKNUM(N167) -> 1 | Q167: ENTREGUE
A168: CONSERV | B168: 1066 | C168: 45617 | D168: =WEEKNUM(C168) -> 47 | E168: HAVANNA | F168: LM PALMAS LTDA | G168: CAMISETA MALHA 100% ALGODÃO BABY LOOK | H168: CAMISETA | I168: LEVE | J168: 18 | K168: 36.75 | L168: =K168*J168 -> 661.5 | M168: 0 | N168: 45636 | O168: =WEEKNUM(N168) -> 50 | Q168: ENTREGUE
A169: CONSERV | B169: 1066 | C169: 45617 | D169: =WEEKNUM(C169) -> 47 | E169: HAVANNA | F169: LM PALMAS LTDA | G169: CAMISETA MALHA 100% ALGODÃO | H169: CAMISETA | I169: LEVE | J169: 8 | K169: 36.75 | L169: =K169*J169 -> 294 | M169: 0 | N169: 45636 | O169: =WEEKNUM(N169) -> 50 | Q169: ENTREGUE
A170: CONSERV | B170: 1066 | C170: 45617 | D170: =WEEKNUM(C170) -> 47 | E170: HAVANNA | F170: LM PALMAS LTDA | G170: AVENTAL OXFORD MODELO PADRÃO | H170: AVENTAL | I170: LEVE | J170: 10 | K170: 25 | L170: =K170*J170 -> 250 | M170: 0 | N170: 45636 | O170: =WEEKNUM(N170) -> 50 | Q170: ENTREGUE
A171: CONSERV | B171: 1066 | C171: 45617 | D171: =WEEKNUM(C171) -> 47 | E171: HAVANNA | F171: LM PALMAS LTDA | G171: FAIXA DE CABELO | H171: FAIXA | I171: LEVE | J171: 10 | K171: 21 | L171: =K171*J171 -> 210 | M171: 0 | N171: 45636 | O171: =WEEKNUM(N171) -> 50 | Q171: ENTREGUE
A172: CONSERV | B172: 1116 | C172: 45622 | D172: =WEEKNUM(C172) -> 48 | E172: HAVANNA | F172: LBP LANCHONETE, CAFETERIA E COMÉRCIO | G172: AVENTAL OXFORD MODELO PADRÃO | H172: AVENTAL | I172: LEVE | J172: 13 | K172: 25 | L172: =K172*J172 -> 325 | M172: 0 | N172: 45681 | O172: =WEEKNUM(N172) -> 4 | Q172: ENTREGUE
A173: CONSERV | B173: 1116 | C173: 45622 | D173: =WEEKNUM(C173) -> 48 | E173: HAVANNA | F173: LBP LANCHONETE, CAFETERIA E COMÉRCIO | G173: CAMISETA MALHA 100% ALGODÃO BABY LOOK | H173: CAMISETA | I173: LEVE | J173: 7 | K173: 36.75 | L173: =K173*J173 -> 257.25 | M173: 0 | N173: 45681 | O173: =WEEKNUM(N173) -> 4 | Q173: ENTREGUE
... A177: CONSERV | B177: 1076 | C177: 45623 | D177: =WEEKNUM(C177) -> 48 | E177: HAVANNA | F177: HAVANNA IMIGRANTES | G177: FAIXA DE CABELO | H177: FAIXA | I177: LEVE | J177: 5 | K177: 21 | L177: =K177*J177 -> 105 | M177: 0 | N177: 45625 | O177: =WEEKNUM(N177) -> 48 | Q177: ENTREGUE
A178: CONSERV | B178: 1077 | C178: 45628 | D178: =WEEKNUM(C178) -> 49 | E178: COSMÉTICO | F178: SARAH K | G178: KIMONO CETIM | H178: KIMONO | I178: PESADA | J178: 100 | M178: 0 | N178: 45663 | O178: =WEEKNUM(N178) -> 2 | P178: OK | Q178: ENTREGUE | R178: =J178*0.25 -> 25 | S178: =J178*1.5 -> 150 | T178: =J178*5.27 -> 527 | U178: =J178*0.5 -> 50 | V178: =R178+S178+T178+U178 -> 752
A179: CONSERV | B179: 1081 | C179: 45632 | D179: =WEEKNUM(C179) -> 49 | E179: HAVANNA | F179: CAFÉ DEL PLATA | G179: CAMISETA MALHA 100% ALGODÃO BABY LOOK | H179: CAMISETA | I179: LEVE | J179: 4 | K179: 36.75 | L179: =K179*J179 -> 147 | M179: 0 | N179: 45636 | O179: =WEEKNUM(N179) -> 50 | Q179: ENTREGUE
A180: CONSERV | B180: 1081 | C180: 45632 | D180: =WEEKNUM(C180) -> 49 | E180: HAVANNA | F180: CAFÉ DEL PLATA | G180: CAMISETA MALHA 100% ALGODÃO | H180: CAMISETA | I180: LEVE | J180: 18 | K180: 36.75 | L180: =K180*J180 -> 661.5 | M180: 0 | N180: 45636 | O180: =WEEKNUM(N180) -> 50 | Q180: ENTREGUE
A181: CONSERV | B181: 1081 | C181: 45632 | D181: =WEEKNUM(C181) -> 49 | E181: HAVANNA | F181: CAFÉ DEL PLATA | G181: AVENTAL OXFORD MODELO PADRÃO | H181: AVENTAL | I181: LEVE | J181: 10 | K181: 25 | L181: =K181*J181 -> 250 | M181: 0 | N181: 45636 | O181: =WEEKNUM(N181) -> 50 | Q181: ENTREGUE
A182: CONSERV | B182: 1081 | C182: 45632 | D182: =WEEKNUM(C182) -> 49 | E182: HAVANNA | F182: CAFÉ DEL PLATA | G182: FAIXA DE CABELO | H182: FAIXA | I182: LEVE | J182: 4 | K182: 21 | L182: =K182*J182 -> 84 | M182: 0 | N182: 45636 | O182: =WEEKNUM(N182) -> 50 | Q182: ENTREGUE
A183: CONSERV | B183: 1082 | C183: 45632 | D183: =WEEKNUM(C183) -> 49 | E183: HAVANNA | F183: DGA DOCES | G183: AVENTAL OXFORD MODELO PADRÃO | H183: AVENTAL | I183: LEVE | J183: 40 | K183: 25 | L183: =K183*J183 -> 1000 | M183: 0 | N183: 45659 | O183: =WEEKNUM(N183) -> 1 | Q183: ENTREGUE
A184: CONSERV | B184: 1082 | C184: 45632 | D184: =WEEKNUM(C184) -> 49 | E184: HAVANNA | F184: DGA DOCES | G184: CAMISETA MALHA 100% ALGODÃO | H184: CAMISETA | I184: LEVE | J184: 75 | K184: 36.75 | L184: =K184*J184 -> 2756.25 | M184: 0 | N184: 45659 | O184: =WEEKNUM(N184) -> 1 | Q184: ENTREGUE
A185: CONSERV | B185: 1082 | C185: 45632 | D185: =WEEKNUM(C185) -> 49 | E185: HAVANNA | F185: DGA DOCES | G185: AVENTAL OXFORD MODELO PADRÃO | H185: AVENTAL | I185: LEVE | J185: 40 | K185: 25 | L185: =J185*K185 -> 1000 | M185: 0 | N185: 45663 | O185: =WEEKNUM(N185) -> 2 | P185: OK | Q185: ENTREGUE | R185: =J185*0.25 -> 10 | S185: =J185*0.7 -> 28 | T185: =J185*1.5 -> 60 | U185: =J185*0.5 -> 20 | V185: =R185+S185+T185+U185 -> 118
A186: CONSERV | B186: 1082 | C186: 45632 | D186: =WEEKNUM(C186) -> 49 | E186: HAVANNA | F186: DGA DOCES | G186: CAMISETA MALHA 100% ALGODÃO | H186: CAMISETA | I186: LEVE | J186: 75 | K186: 36.75 | L186: =J186*K186 -> 2756.25 | M186: 0 | N186: 45663 | O186: =WEEKNUM(N186) -> 2 | P186: OK | Q186: ENTREGUE | R186: =J186*0.25 -> 18.75 | S186: =R186*1.5 -> 28.125 | T186: =J186*1.5 -> 112.5 | U186: =J186*0.5 -> 37.5 | V186: =R186+S186+T186+U186 -> 196.875
A187: CONSERV | B187: 651 | C187: 45632 | D187: =WEEKNUM(C187) -> 49 | E187: COSMÉTICO | F187: LIZZE | G187: NECESSAIRE NYLON 70 PHOTON LIZZE | H187: NECESSAIRE | I187: PESADA | J187: 2000 | M187: 0 | N187: 45667 | O187: =WEEKNUM(N187) -> 2 | P187: OK | Q187: ENTREGUE | R187: =J187*0.25 -> 500 | S187: =J187*1 -> 2000 | T187: =J187*1.5 -> 3000 | U187: =J187*0.5 -> 1000 | V187: =R187+S187+T187+U187 -> 6500
A188: CONSERV | B188: 651 | C188: 45632 | D188: =WEEKNUM(C188) -> 49 | E188: COSMÉTICO | F188: LIZZE | G188: NECESSAIRE NYLON 70 EXTREME | H188: NECESSAIRE | I188: PESADA | J188: 2000 | M188: 0 | N188: 45667 | O188: =WEEKNUM(N188) -> 2 | P188: OK | Q188: ENTREGUE | R188: =J188*0.25 -> 500 | S188: =J188*1 -> 2000 | T188: =J188*1.5 -> 3000 | U188: =J188*0.5 -> 1000 | V188: =R188+S188+T188+U188 -> 6500
A189: CONSERV | B189: 1083 | C189: 45635 | D189: =WEEKNUM(C189) -> 50 | E189: HAVANNA | F189: DOCES E DOCES MF LTDA | G189: AVENTAL OXFORD MODELO PADRÃO | H189: AVENTAL | I189: LEVE | J189: 10 | K189: 25 | L189: =K189*J189 -> 250 | M189: 0 | N189: 45665 | O189: =WEEKNUM(N189) -> 2 | Q189: ENTREGUE
A190: CONSERV | B190: 1083 | C190: 45635 | D190: =WEEKNUM(C190) -> 50 | E190: HAVANNA | F190: DOCES E DOCES MF LTDA | G190: FAIXA DE CABELO | H190: FAIXA | I190: LEVE | J190: 10 | K190: 21 | L190: =K190*J190 -> 210 | M190: 0 | N190: 45665 | O190: =WEEKNUM(N190) -> 2 | Q190: ENTREGUE
A191: CONSERV | B191: 1084 | C191: 45637 | D191: =WEEKNUM(C191) -> 50 | E191: COSMÉTICO | F191: SARAH K | G191: AVENTAL NY 210 | H191: AVENTAL | I191: LEVE | J191: 150 | M191: 0 | N191: 45663 | O191: =WEEKNUM(N191) -> 2 | P191: OK | Q191: ENTREGUE | R191: =J191*0.25 -> 37.5 | S191: =J191*0.7 -> 105 | T191: =J191*1.84 -> 276 | U191: =J191*0.5 -> 75 | V191: =R191+S191+T191+U191 -> 493.5
A192: CONSERV | B192: 654 | C192: 45637 | D192: =WEEKNUM(C192) -> 50 | E192: COMÉRCIO | F192: TAPIS | G192: SACO DE ALGODAO | H192: SACO | I192: LEVE | J192: 200 | M192: 0 | N192: 45664 | O192: =WEEKNUM(N192) -> 2 | P192: OK | Q192: ENTREGUE | R192: =J192*0.25 -> 50 | S192: =J192*0.5 -> 100 | T192: =J192*0.8 -> 160 | U192: =J192*0.5 -> 100 | V192: =R192+S192+T192+U192 -> 410
A193: CONSERV | B193: 655 | C193: 45637 | D193: =WEEKNUM(C193) -> 50 | E193: COMÉRCIO | F193: VOICER STORE (AUDIO VOICER) | G193: NECESSAIRE NY PLASTIFICADO | H193: NECESSAIRE | I193: PESADA | J193: 300 | K193: 23 | L193: =K193*J193 -> 6900 | M193: 0 | N193: 45670 | O193: =WEEKNUM(N193) -> 3 | P193: OK | Q193: ENTREGUE | R193: =J193*0.25 -> 75 | S193: =J193*0.6 -> 180 | T193: =J193*5 -> 1500 | U193: =J193*0.5 -> 150 | V193: =R193+S193+T193+U193 -> 1905
A194: CONSERV | B194: 658 | C194: 45642 | D194: =WEEKNUM(C194) -> 51 | E194: PET | F194: LDM ESPECIALIDADES PELONCIO | G194: JALECO BICOLOR TACTEL | H194: JALECO | I194: LEVE | J194: 50 | M194: 0 | N194: 45674 | O194: =WEEKNUM(N194) -> 3 | P194: OK | Q194: ENTREGUE | R194: =J194*0.25 -> 12.5 | T194: =J194*10 -> 500 | U194: =J194*0.5 -> 25 | V194: =R194+S194+T194+U194 -> 537.5
A195: CONSERV | B195: 659 | C195: 45645 | D195: =WEEKNUM(C195) -> 51 | E195: COSMÉTICO | F195: KPRO | G195: AVENTAL LONITA COM COURO | H195: AVENTAL | I195: PESADA | J195: 1100 | M195: 0 | N195: 45671 | O195: =WEEKNUM(N195) -> 3 | P195: OK | Q195: ENTREGUE | R195: =J195*0.25 -> 275 | S195: =J195*1 -> 1100 | T195: =J195*3 -> 3300 | U195: =J195*0.5 -> 550 | V195: =R195+S195+T195+U195 -> 5225
A196: CONSERV | B196: 1094 | C196: 45652 | D196: =WEEKNUM(C196) -> 52 | E196: PET | F196: GRANFOOD | G196: SACOLA ALGODAO BRIM 40L X 45A | H196: SACOLA | I196: LEVE | J196: 250 | M196: 0 | N196: 45701 | O196: =WEEKNUM(N196) -> 7 | P196: OK | Q196: ENTREGUE | R196: =J196*0.25 -> 62.5 | S196: =J196*0.6 -> 150 | T196: =J196*1 -> 250 | U196: =J196*0.5 -> 125 | V196: =R196+S196+T196+U196 -> 587.5
A197: CONSERV | B197: 1094 | C197: 45652 | D197: =WEEKNUM(C197) -> 52 | E197: PET | F197: GRANDFOOD (PREMIER) | G197: AVENTAL NY EMBORRACHADO AZUL | H197: AVENTAL | I197: LEVE | J197: 1000 | M197: 0 | N197: 45664 | O197: =WEEKNUM(N197) -> 2 | P197: OK | Q197: ENTREGUE | R197: =J197*0.25 -> 250 | S197: =J197*1 -> 1000 | T197: =J197*1.65 -> 1650 | U197: =J197*0.5 -> 500 | V197: =R197+S197+T197+U197 -> 3400
A198: LETICIA | B198: 1093 | C198: 45652 | D198: =WEEKNUM(C198) -> 52 | E198: PET | F198: GRANDFOOD (PREMIER) | G198: PASTA NOTEBOOK | H198: PASTA | I198: PESADA | J198: 270 | K198: 40 | L198: 0 | M198: 0 | N198: 45706 | O198: =WEEKNUM(N198) -> 8 | Q198: ENTREGUE | R198: =J198*0.25 -> 67.5 | S198: =J198*0.7 -> 189 | T198: =J198*3 -> 810 | U198: =J198*0.5 -> 135 | V198: =R198+S198+T198+U198 -> 1201.5
A199: CONSERV | B199: 661 | C199: 45659 | D199: =WEEKNUM(C199) -> 1 | E199: COSMÉTICO | F199: M.D BOSO (PROHALL) | G199: CAPA DE CORTE TACTEL 1,40X 1,50 | H199: CAPA | I199: LEVE | J199: 200 | K199: 24.5 | L199: =K199*J199 -> 4900 | M199: 0 | N199: 45677 | O199: =WEEKNUM(N199) -> 4 | P199: OK | Q199: ENTREGUE | R199: =J199*0.25 -> 50 | S199: =J199*1 -> 200 | T199: =J199*1.5 -> 300 | U199: =J199*0.5 -> 100 | V199: =R199+S199+T199+U199 -> 650
A200: CONSERV | B200: 661 | C200: 45659 | D200: =WEEKNUM(C200) -> 1 | E200: COSMÉTICO | F200: MER CASTRO COMERCIO (MARIA SUBLIME) | G200: SAQUINHO DE ALGODÃO | H200: SAQUINHO | I200: LEVE | J200: 600 | M200: 0 | N200: 45673 | O200: =WEEKNUM(N200) -> 3 | P200: OK | Q200: ENTREGUE | R200: =J200*0.25 -> 150 | U200: =J200*0.5 -> 300 | V200: =R200+S200+T200+U200 -> 450
A201: CONSERV | B201: 1102 | C201: 45663 | D201: =WEEKNUM(C201) -> 2 | E201: HAVANNA | F201: CONCI & TEIXEIRA ALIMENTOS LTDA (HAVANNA MG) | G201: AVENTAL OXFORD MODELO PADRÃO | H201: AVENTAL | I201: LEVE | J201: 2 | K201: 25 | L201: =J201*K201 -> 50 | M201: 0 | N201: 45693 | O201: =WEEKNUM(N201) -> 6 | P201: OK | Q201: ENTREGUE | R201: =J201*0.25 -> 0.5 | S201: =J201*0.7 -> 1.4 | T201: =J201*1.5 -> 3 | U201: =J201*0.5 -> 1 | V201: =R201+S201+T201+U201 -> 5.9
A202: CONSERV | B202: 1102 | C202: 45663 | D202: =WEEKNUM(C202) -> 2 | E202: HAVANNA | F202: CONCI & TEIXEIRA ALIMENTOS LTDA (HAVANNA MG) | G202: FAIXA DE CABELO | H202: FAIXA | I202: LEVE | J202: 2 | K202: 21 | L202: =J202*K202 -> 42 | M202: 0 | N202: 45693 | O202: =WEEKNUM(N202) -> 6 | P202: OK | Q202: ENTREGUE | R202: =J202*0.25 -> 0.5 | S202: =J202*1 -> 2 | T202: =J202*1.2 -> 2.4 | U202: =J202*0.5 -> 1 | V202: =R202+S202+T202+U202 -> 5.9
A203: CONSERV | B203: 1102 | C203: 45663 | D203: =WEEKNUM(C203) -> 2 | E203: HAVANNA | F203: CONCI & TEIXEIRA ALIMENTOS LTDA (HAVANNA MG) | G203: CAMISETA MALHA 100% ALGODÃO | H203: CAMISETA | I203: LEVE | J203: 2 | K203: 36.75 | L203: =K203*J203 -> 73.5 | M203: 0 | N203: 45693 | O203: =WEEKNUM(N203) -> 6 | P203: OK | Q203: ENTREGUE | R203: =J203*0.25 -> 0.5 | S203: =R203*1.5 -> 0.75 | T203: =J203*1.5 -> 3 | U203: =J203*0.5 -> 1 | V203: =R203+S203+T203+U203 -> 5.25
A204: CONSERV | B204: 1102 | C204: 45663 | D204: =WEEKNUM(C204) -> 2 | E204: HAVANNA | F204: CONCI & TEIXEIRA ALIMENTOS LTDA (HAVANNA MG) | G204: BABY LOOK FEMININA MALHA 100% ALGODAO | H204: BABY LOOK | I204: LEVE | J204: 6 | K204: 36.75 | L204: =K204*J204 -> 220.5 | M204: 0 | N204: 45693 | O204: =WEEKNUM(N204) -> 6 | P204: OK | Q204: ENTREGUE | R204: =J204*0.25 -> 1.5 | S204: =R204*1.5 -> 2.25 | T204: =J204*1.5 -> 9 | U204: =J204*0.5 -> 3 | V204: =R204+S204+T204+U204 -> 15.75
A205: CONSERV | B205: 1102 | C205: 45663 | D205: =WEEKNUM(C205) -> 2 | E205: HAVANNA | F205: CONCI & TEIXEIRA ALIMENTOS LTDA (HAVANNA MG) | G205: CAMISETA MALHA 100% ALGODÃO | H205: CAMISETA | I205: LEVE | J205: 2 | K205: 36.75 | L205: =K205*J205 -> 73.5 | M205: 0 | N205: 45693 | O205: =WEEKNUM(N205) -> 6 | P205: OK | Q205: ENTREGUE | R205: =J205*0.25 -> 0.5 | S205: =R205*1.5 -> 0.75 | T205: =J205*1.5 -> 3 | U205: =J205*0.5 -> 1 | V205: =R205+S205+T205+U205 -> 5.25
A206: CONSERV | B206: 663 | C206: 45663 | D206: =WEEKNUM(C206) -> 2 | E206: PET | F206: LDM ESPECIALIDADES PELONCIO | G206: AVENTAL NY EMBORRACHADO | H206: AVENTAL | I206: LEVE | J206: 250 | M206: 0 | N206: 45677 | O206: =WEEKNUM(N206) -> 4 | Q206: ENTREGUE | R206: =J206*0.25 -> 62.5 | S206: =J206*1 -> 250 | T206: =J206*1.84 -> 460 | U206: =J206*0.5 -> 125 | V206: =R206+S206+T206+U206 -> 897.5
A207: CONSERV | B207: 664 | C207: 45665 | D207: =WEEKNUM(C207) -> 2 | E207: COMÉRCIO | F207: ALTEGIO BRASIL | G207: CAPA DE CORTE TACTEL 1,40X 1,50 | H207: CAPA | I207: LEVE | J207: 20 | M207: 0 | N207: 45695 | O207: =WEEKNUM(N207) -> 6 | P207: OK | Q207: ENTREGUE | R207: =J207*0.25 -> 5 | S207: =J207*1 -> 20 | T207: =J207*1.5 -> 30 | U207: =J207*0.5 -> 10 | V207: =R207+S207+T207+U207 -> 65
A208: CONSERV | B208: 664 | C208: 45665 | D208: =WEEKNUM(C208) -> 2 | E208: COMÉRCIO | F208: ALTEGIO BRASIL | G208: POLO PIQUET | H208: POLO | I208: LEVE | J208: 12 | M208: 0 | N208: 45695 | O208: =WEEKNUM(N208) -> 6 | P208: OK | Q208: ENTREGUE | R208: =J208*0.25 -> 3 | S208: =J208*1 -> 12 | T208: =J208*3 -> 36 | U208: =J208*0.5 -> 6 | V208: =R208+S208+T208+U208 -> 57
A209: CONSERV | B209: 664 | C209: 45665 | D209: =WEEKNUM(C209) -> 2 | E209: COMÉRCIO | F209: ALTEGIO BRASIL | G209: CAMISETA MALHA PV | H209: CAMISETA | I209: LEVE | J209: 12 | M209: 0 | N209: 45695 | O209: =WEEKNUM(N209) -> 6 | P209: OK | Q209: ENTREGUE | R209: =J209*0.25 -> 3 | S209: =R209*1.5 -> 4.5 | T209: =J209*1.5 -> 18 | U209: =J209*0.5 -> 6 | V209: =R209+S209+T209+U209 -> 31.5
A210: CONSERV | B210: 1104 | C210: 45666 | D210: =WEEKNUM(C210) -> 2 | E210: COMÉRCIO | F210: GRAM INDUSTRIA | G210: LENÇO SUBLIMADO | H210: LENÇO | I210: LEVE | J210: 1000 | M210: 0 | N210: 45688 | O210: =WEEKNUM(N210) -> 5 | P210: ok | Q210: ENTREGUE | R210: =J210*0.25 -> 250 | T210: =J210*1.5 -> 1500 | U210: =J210*0.5 -> 500 | V210: =R210+S210+T210+U210 -> 2250
A211: CONSERV | B211: 665 | C211: 45670 | D211: =WEEKNUM(C211) -> 3 | E211: COMÉRCIO | F211: MULTILIXO | G211: SACOLA ALGODAO 30,5 X 37,5 | H211: SACOLA | I211: LEVE | J211: 1000 | M211: 0 | N211: 45695 | O211: =WEEKNUM(N211) -> 6 | P211: OK | Q211: ENTREGUE | R211: =J211*0.25 -> 250 | S211: =J211*0.6 -> 600 | T211: =J211*1 -> 1000 | U211: =J211*0.5 -> 500 | V211: =R211+S211+T211+U211 -> 2350
A212: CONSERV | B212: 667 | C212: 45670 | D212: =WEEKNUM(C212) -> 3 | E212: PET | F212: PET SPA | G212: AVENTAL NY EMBORRACHADO | H212: AVENTAL | I212: LEVE | J212: 240 | K212: 25 | L212: =J212*K212 -> 6000 | M212: 0 | N212: 45698 | O212: =WEEKNUM(N212) -> 7 | Q212: ENTREGUE | R212: =J212*0.25 -> 60 | S212: =J212*1 -> 240 | T212: =J212*1.84 -> 441.6 | U212: =J212*0.5 -> 120 | V212: =R212+S212+T212+U212 -> 861.6
A213: CONSERV | B213: 669 | C213: 45672 | D213: =WEEKNUM(C213) -> 3 | E213: COMÉRCIO | F213: PAULO F BRAZ | G213: CAMISETA MALHA 100% ALGODÃO | H213: CAMISETA | I213: LEVE | J213: 20 | M213: 0 | N213: 45700 | O213: =WEEKNUM(N213) -> 7 | Q213: ENTREGUE | R213: =J213*0.25 -> 5 | S213: =R213*1.5 -> 7.5 | T213: =J213*1.5 -> 30 | U213: =J213*0.5 -> 10 | V213: =R213+S213+T213+U213 -> 52.5
A214: LETICIA | B214: 1109 | C214: 45673 | D214: =WEEKNUM(C214) -> 3 | E214: COSMÉTICO | F214: CRISTINA BRASILIAN | G214: AVENTAL NY 210 | H214: AVENTAL | I214: LEVE | J214: 1000 | K214: 18 | L214: =J214*K214 -> 18000 | M214: 0 | N214: 45705 | O214: =WEEKNUM(N214) -> 8 | Q214: ENTREGUE | R214: =J214*0.25 -> 250 | S214: =J214*0.7 -> 700 | T214: =J214*1.84 -> 1840 | U214: =J214*0.5 -> 500 | V214: =R214+S214+T214+U214 -> 3290
A215: LETICIA | B215: 1109 | C215: 45673 | D215: =WEEKNUM(C215) -> 3 | E215: COSMÉTICO | F215: CRISTINA BRASILIAN | G215: CAPA DE CORTE TACTEL 1,40X 1,50 | H215: CAPA | I215: LEVE | J215: 1000 | K215: 24.5 | L215: =J215*K215 -> 24500 | M215: 0 | N215: 45705 | O215: =WEEKNUM(N215) -> 8 | Q215: ENTREGUE | R215: =J215*0.25 -> 250 | S215: =J215*1 -> 1000 | T215: =J215*1.5 -> 1500 | U215: =J215*0.5 -> 500 | V215: =R215+S215+T215+U215 -> 3250
A216: CONSERV | B216: 670 | C216: 45673 | D216: =WEEKNUM(C216) -> 3 | E216: PET | F216: LDM ESPECIALIDADES PELONCIO | G216: AVENTAL NY EMBORRACHADO | H216: AVENTAL | I216: LEVE | J216: 250 | M216: 0 | N216: 45701 | O216: =WEEKNUM(N216) -> 7 | Q216: ENTREGUE | R216: =J216*0.25 -> 62.5 | S216: =J216*1 -> 250 | T216: =J216*1.84 -> 460 | U216: =J216*0.5 -> 125 | V216: =R216+S216+T216+U216 -> 897.5
A217: CONSERV | B217: 1110 | C217: 45674 | D217: =WEEKNUM(C217) -> 3 | E217: COSMÉTICO | F217: BEUATY FAIR | G217: AVENTAL BARBEIRO COURO SINTETICO | H217: AVENTAL | I217: PESADA | J217: 100 | K217: 67 | L217: =J217*K217 -> 6700 | M217: 0 | N217: 45698 | O217: =WEEKNUM(N217) -> 7 | Q217: ENTREGUE | R217: =J217*0.25 -> 25 | S217: =J217*1 -> 100 | T217: =J217*3 -> 300 | U217: =J217*0.5 -> 50 | V217: =R217+S217+T217+U217 -> 475
A218: CONSERV | B218: 1111 | C218: 45674 | D218: =WEEKNUM(C218) -> 3 | E218: PET | F218: GRANFOOD | G218: SACOLA NYLON 600 35X 40 X 18 | H218: SACOLA | I218: PESADA | J218: 300 | M218: 0 | N218: 45675 | O218: =WEEKNUM(N218) -> 3 | Q218: ENTREGUE | R218: =J218*0.25 -> 75 | S218: =J218*0.6 -> 180 | T218: =J218*1.5 -> 450 | U218: =J218*0.5 -> 150 | V218: =R218+S218+T218+U218 -> 855
A219: CONSERV | B219: 1108 | C219: 45674 | D219: =WEEKNUM(C219) -> 3 | E219: PET | F219: GRANFOOD | G219: CAMISETA GOLA CARECA | H219: CAMISETA | I219: LEVE | J219: =135+140 -> 275 | K219: 21 | L219: =J219*K219 -> 5775 | M219: 0 | N219: 45716 | O219: =WEEKNUM(N219) -> 9 | Q219: ENTREGUE | R219: =J219*0.25 -> 68.75 | S219: =R219*1.5 -> 103.125 | T219: =J219*1.5 -> 412.5 | U219: =J219*0.5 -> 137.5 | V219: =R219+S219+T219+U219 -> 721.875
A220: CONSERV | B220: 1108 | C220: 45674 | D220: =WEEKNUM(C220) -> 3 | E220: PET | F220: GRANFOOD | G220: CAMISETA GOLA CARECA | H220: CAMISETA | I220: LEVE | J220: =140+160 -> 300 | K220: 21 | L220: =J220*K220 -> 6300 | M220: 0 | N220: 45716 | O220: =WEEKNUM(N220) -> 9 | Q220: ENTREGUE | R220: =J220*0.25 -> 75 | S220: =R220*1.5 -> 112.5 | T220: =J220*1.5 -> 450 | U220: =J220*0.5 -> 150 | V220: =R220+S220+T220+U220 -> 787.5
A221: CONSERV | B221: 1107 | C221: 45674 | D221: =WEEKNUM(C221) -> 3 | E221: PET | F221: GRANFOOD | G221: CAPA DE CADEIRA HELANCA 40X40 | H221: CAPA | I221: LEVE | J221: 250 | M221: 0 | N221: 45702 | O221: =WEEKNUM(N221) -> 7 | Q221: ENTREGUE | R221: =J221*0.25 -> 62.5 | T221: =J221*1 -> 250 | U221: =J221*0.5 -> 125 | V221: =R221+S221+T221+U221 -> 437.5
A222: CONSERV | B222: 1107 | C222: 45674 | D222: =WEEKNUM(C222) -> 3 | E222: PET | F222: GRANFOOD | G222: CAPA DE CADEIRA HELANCA 40X40 | H222: CAPA | I222: LEVE | J222: 500 | K222: 11.5 | L222: =J222*K222 -> 5750 | M222: 0 | N222: 45702 | O222: =WEEKNUM(N222) -> 7 | Q222: ENTREGUE | R222: =J222*0.25 -> 125 | T222: =J222*1 -> 500 | U222: =J222*0.5 -> 250 | V222: =R222+S222+T222+U222 -> 875
A223: CONSERV | B223: 1114 | C223: 45678 | D223: =WEEKNUM(C223) -> 4 | E223: HAVANNA | F223: D R DOCES E CAFES | G223: CAMISETA MALHA 100% ALGODÃO | H223: CAMISETA | I223: LEVE | J223: 5 | K223: 36.75 | L223: =K223*J223 -> 183.75 | M223: 0 | N223: 45711 | O223: =WEEKNUM(N223) -> 9 | Q223: ENTREGUE | R223: =J223*0.25 -> 1.25 | S223: =R223*1.5 -> 1.875 | T223: =J223*1.5 -> 7.5 | U223: =J223*0.5 -> 2.5 | V223: =R223+S223+T223+U223 -> 13.125
A224: CONSERV | B224: 1114 | C224: 45678 | D224: =WEEKNUM(C224) -> 4 | E224: HAVANNA | F224: D R DOCES E CAFES | G224: CAMISETA MALHA 100% ALGODÃO | H224: CAMISETA | I224: LEVE | J224: 4 | K224: 36.75 | L224: =K224*J224 -> 147 | M224: 0 | N224: 45711 | O224: =WEEKNUM(N224) -> 9 | Q224: ENTREGUE | R224: =J224*0.25 -> 1 | S224: =R224*1.5 -> 1.5 | T224: =J224*1.5 -> 6 | U224: =J224*0.5 -> 2 | V224: =R224+S224+T224+U224 -> 10.5
A225: CONSERV | B225: 1114 | C225: 45678 | D225: =WEEKNUM(C225) -> 4 | E225: HAVANNA | F225: D R DOCES E CAFES | G225: BLUSA DE MOLETOM | H225: MOLETOM | I225: LEVE | J225: 4 | K225: 85 | L225: =K225*J225 -> 340 | M225: 0 | N225: 45711 | O225: =WEEKNUM(N225) -> 9 | Q225: ENTREGUE | R225: =J225*0.25 -> 1 | S225: =PRODUCT(1.5,J225) -> 6 | T225: =PRODUCT(1.5,J225) -> 6 | U225: =J225*0.5 -> 2 | V225: =R225+S225+T225+U225 -> 15
A226: CONSERV | B226: 1114 | C226: 45678 | D226: =WEEKNUM(C226) -> 4 | E226: HAVANNA | F226: D R DOCES E CAFES | G226: FAIXA DE CABELO | H226: FAIXA | I226: LEVE | J226: 2 | K226: 21 | L226: =K226*J226 -> 42 | M226: 0 | N226: 45711 | O226: =WEEKNUM(N226) -> 9 | Q226: ENTREGUE | R226: =J226*0.25 -> 0.5 | S226: =J226*1 -> 2 | T226: =J226*1.2 -> 2.4 | U226: =J226*0.5 -> 1 | V226: =R226+S226+T226+U226 -> 5.9
A227: LETICIA | B227: 686 | C227: 45679 | D227: =WEEKNUM(C227) -> 4 | E227: COMÉRCIO | F227: CASTLE PRODUTOS | G227: AVENTAL OXFORD MODELO PADRÃO | H227: AVENTAL | I227: LEVE | J227: 100 | K227: 18.5 | L227: =J227*K227 -> 1850 | M227: 0 | N227: 45722 | O227: =WEEKNUM(N227) -> 10 | Q227: ENTREGUE | R227: =J227*0.25 -> 25 | S227: =J227*0.7 -> 70 | T227: =J227*1.84 -> 184 | U227: =J227*0.5 -> 50 | V227: =R227+S227+T227+U227 -> 329
A228: LETICIA | B228: 1113 | C228: 45679 | D228: =WEEKNUM(C228) -> 4 | E228: PET | F228: CEQ (PET SOCIETY) | G228: AVENTAL NYLON EMBORRACHADO CA 45305 | H228: AVENTAL | I228: LEVE | J228: 2500 | K228: 23.5 | L228: =J228*K228 -> 58750 | M228: 0 | N228: 45733 | O228: =WEEKNUM(N228) -> 12 | Q228: ENTREGUE | R228: =J228*0.25 -> 625 | S228: =J228*1 -> 2500 | T228: =J228*1.65 -> 4125 | U228: =J228*0.5 -> 1250 | V228: =R228+S228+T228+U228 -> 8500
A229: CONSERV | B229: 1118 | C229: 45679 | D229: =WEEKNUM(C229) -> 4 | E229: COMÉRCIO | F229: MARKET BRINDES | G229: SACOLA BAGUN SUBLIMADA | H229: SACOLA | I229: PESADA | J229: 301 | M229: 0 | N229: 45707 | O229: =WEEKNUM(N229) -> 8 | Q229: ENTREGUE | R229: =J229*0.25 -> 75.25 | U229: =J229*0.5 -> 150.5 | V229: =R229+S229+T229+U229 -> 225.75
A230: CONSERV | B230: 671 | C230: 45680 | D230: =WEEKNUM(C230) -> 4 | E230: PET | F230: BUBBLES PET | G230: AVENTAL NY EMBORRACHADO | H230: AVENTAL | I230: AMBAS | J230: 250 | L230: =J230*K230 -> 0 | M230: 0 | N230: 45708 | O230: =WEEKNUM(N230) -> 8 | Q230: ENTREGUE | R230: =J230*0.25 -> 62.5 | S230: =J230*1 -> 250 | T230: =J230*1.84 -> 460 | U230: =J230*0.5 -> 125 | V230: =R230+S230+T230+U230 -> 897.5
...

Sheet VENDAS 2026
A1: CARTEIRA EM PRODUÇÃO | D1: TICKTI MÉDIO
A2: Peças | B2: ='PCP + MO '!J1629 -> 24489 | D2: =B3/B2 -> 17.136449
A3: Faturar | B3: ='PCP + MO '!L1629 -> 419654.5 | I3: —
A4: Liquidar | B4: ='PCP + MO '!M1629 -> 246959.5
A6: VENDAS 2026
A7: MÊS | B7: QUANT PEDIDOS | C7: ITENS | D7: VALOR TOTAL | E7: TICTIK MÉDIO
A8: JANEIRO | B8: 39 | C8: 13275 | D8: 257139.2 | E8: =D8/C8 -> 19.370185
A9: FEVEREIRO | B9: 39 | C9: 12509 | D9: 231893.5 | E9: =D9/C9 -> 18.538133
A10: MARÇO | B10: 55 | C10: 44179 | D10: 588929 | E10: =D10/C10 -> 13.330519
A11: ABRIL | B11: 31 | C11: 13879 | D11: 228088.5 | E11: =D11/C11 -> 16.434073
A12: MAIO | B12: 43 | C12: 14040 | D12: 316137.8 | E12: =D12/C12 -> 22.516937
A13: JUNHO | B13: 41 | C13: 9241 | D13: 160954.25 | E13: =D13/C13 -> 17.417406
A14: JULHO | B14: 51 | C14: 23992 | D14: 444060.04 | E14: =D14/C14 -> 18.508671
A15: AGOSTO
A16: SETEMBRO
A17: OUTUBRO
A18: NOVEMBRO
A19: DEZEMBRO
A20: TOTAL | B20: =SUM(B8:B19) -> 299 | C20: =SUM(C8:C19) -> 131115 | D20: =SUM(D8:D19) -> 2227202.3

Sheet PEDIDOS EM ABERTO HAVANNA
A1: PEDIDO HAVANNA 237 - HVNN ONE COMERCIO
A2: PRODUTO | B2: TAM | C2: QUANT
A3: POLO FEMININA | B3: P | C3: 1
A4: POLO FEMININA | B4: M | C4: 1
A5: POLO FEMININA | B5: G | C5: 1
A6: POLO | B6: M | C6: 1
A8: PEDIDO HAVANNA 241 - PATAGONIA CAFÉ
A9: PRODUTO | B9: TAM | C9: QUANT
A10: CAMISETA | B10: G | C10: 6
A11: CAMISETA | B11: GG | C11: 6
A12: CAMISETA MANGA LONGA | B12: G | C12: 1
A13: CAMISETA MANGA LONGA | B13: GG | C13: 1
A14: BLUSA MOLETOM | B14: G | C14: 1
A15: BLUSA MOLETOM | B15: GG | C15: 1
A16: AVENTAL | C16: 4
A18: PEDIDO HAVANNA 244 - CAFÉ E DOCES
A19: PRODUTO | B19: TAM | C19: QUANT
A20: AVENTAL | C20: 6
A21: FAIXA DE CABELO | C21: 4
A22: CAMISETA BABY LOOK | B22: M | C22: 4
A23: CALÇA BRIM | B23: P | C23: 2
A24: CALÇA BRIM | B24: M | C24: 2
A26: PEDIDO HAVANNA 254 - CAPOBIANGO
A27: PRODUTO | B27: TAM | C27: QUANT
A28: BABY LOOK | B28: M | C28: 2
A29: BABY LOOK MANGA LONGA | B29: M | C29: 1
A30: BABY LOOK MANGA LONGA | B30: G | C30: 1
A31: BABY LOOK MANGA LONGA | B31: GG | C31: 1
